[
    {
        "question": "What is the first name of Anne Miller?",
        "query": "SELECT ?firstName WHERE { :anne foaf:firstName ?firstName . }",
        "generated": "What is the first name of Anne Miller } } } } } } } } } } } } } } } } } } } } } } } } } } } } } } } } } } } } } } } } } } } } } } } } } } } } } } } } } } } } } } } } } } } } } } } } } } } } } } } } } } } } } } } } } } } } } } } } } } } } } } } } } } } } } } } } } } } } } } } } } } } } } } } } } } } } } } } } } } } } } } } } } } } } } } } } } } } } } } } } } } } } } } } } } } } } } } } } } } } } } } } } } } } } } } } } } } } } } } } } } } } } } } } } } } } } } } } } } } } } } } } } } } } } } } } } } } } } } } } } } } } } } }"
    },
    {
        "question": "What is the surname of Bob Tanner?",
        "query": "SELECT ?surname WHERE { :bob foaf:surname ?surname . }",
        "generated": "\ucc3e\ucc3e\ucc3e\ucc3e\ucc3e\ucc3e\ucc3e\ucc3e\ucc3e\ucc3e\ucc3e\ucc3e\ucc3e\ucc3e\ucc3e\ucc3e\ucc3e\ucc3e\ucc3e\ucc3e\ucc3e\ucc3e\ucc3e\ucc3e\ucc3e\ucc3e\ucc3e\ucc3e\ucc3e\ucc3e\ucc3e\ucc3e\ucc3e\ucc3e\ucc3e\ucc3e\ucc3e\ucc3e\ucc3e\ucc3e\ucc3e\ucc3e\ucc3e\ucc3e\ucc3e\ucc3e\ucc3e\ucc3e\ucc3e\ucc3e\ucc3e\ucc3e\ucc3e\ucc3e\ucc3e\ucc3e\ucc3e\ucc3e\ucc3e\ucc3e\ucc3e\ucc3e\ucc3e\ucc3e\ucc3e\ucc3e\ucc3e\ucc3e\ucc3e\ucc3e\ucc3e\ucc3e\ucc3e\ucc3e\ucc3e\ucc3e\ucc3e\ucc3e\ucc3e\ucc3e\ucc3e\ucc3e\ucc3e\ucc3e\ucc3e\ucc3e\ucc3e\ucc3e\ucc3e\ucc3e\ucc3e\ucc3e\ucc3e\ucc3e\ucc3e\ucc3e\ucc3e\ucc3e\ucc3e\ucc3e\ucc3e\ucc3e\ucc3e\ucc3e\ucc3e\ucc3e\ucc3e\ucc3e\ucc3e\ucc3e\ucc3e\ucc3e\ucc3e\ucc3e\ucc3e\ucc3e\ucc3e\ucc3e\ucc3e\ucc3e\ucc3e\ucc3e\ucc3e\ucc3e\ucc3e\ucc3e\ucc3e\ucc3e\ucc3e\ucc3e\ucc3e\ucc3e\ucc3e\ucc3e\ucc3e\ucc3e\ucc3e\ucc3e\ucc3e\ucc3e\ucc3e\ucc3e\ucc3e\ucc3e\ucc3e\ucc3e\ucc3e\ucc3e\ucc3e\ucc3e\ucc3e\ucc3e\ucc3e\ucc3e\ucc3e\ucc3e\ucc3e\ucc3e\ucc3e\ucc3e\ucc3e\ucc3e\ucc3e\ucc3e\ucc3e\ucc3e\ucc3e\ucc3e\ucc3e\ucc3e\ucc3e\ucc3e\ucc3e\ucc3e\ucc3e\ucc3e\ucc3e\ucc3e\ucc3e\ucc3e\ucc3e\ucc3e\ucc3e\ucc3e\ucc3e\ucc3e\ucc3e\ucc3e\ucc3e\ucc3e\ucc3e\ucc3e\ucc3e\ucc3e\ucc3e\ucc3e\ucc3e\ucc3e\ucc3e\ucc3e\ucc3e\ucc3e\ucc3e\ucc3e\ucc3e\ucc3e\ucc3e\ucc3e\ucc3e\ucc3e\ucc3e\ucc3e\ucc3e\ucc3e\ucc3e\ucc3e\ucc3e\ucc3e\ucc3e\ucc3e\ucc3e\ucc3e\ucc3e\ucc3e\ucc3e\ucc3e\ucc3e\ucc3e\ucc3e\ucc3e\ucc3e\ucc3e\ucc3e\ucc3e\ucc3e\ucc3e\ucc3e\ucc3e\ucc3e\ucc3e\ucc3e\ucc3e\ucc3e\ucc3e\ucc3e\ucc3e\ucc3e\ucc3e\ucc3e\ucc3e\ucc3e\ucc3e\ucc3e\ucc3e\ucc3e"
    },
    {
        "question": "Which person has a home address in the UK?",
        "query": "SELECT ?person WHERE { ?person vcard:hasAddress [ vcard:country-name 'UK' ] . }",
        "generated": "\ud3ec\ud568 \ud3ec\ud568 \ud3ec\ud568 \ud3ec\ud568 \ud3ec\ud568 \ud3ec\ud568 \ud3ec\ud568 \ud3ec\ud568 \ud3ec\ud568 \ud3ec\ud568 \ud3ec\ud568 \ud3ec\ud568 \ud3ec\ud568 \ud3ec\ud568 \ud3ec\ud568 \ud3ec\ud568 \ud3ec\ud568 \ud3ec\ud568 \ud3ec\ud568 \ud3ec\ud568 \ud3ec\ud568 \ud3ec\ud568 \ud3ec\ud568 \ud3ec\ud568 \ud3ec\ud568 \ud3ec\ud568 \ud3ec\ud568 \ud3ec\ud568 \ud3ec\ud568 \ud3ec\ud568 \ud3ec\ud568 \ud3ec\ud568 \ud3ec\ud568 \ud3ec\ud568 \ud3ec\ud568 \ud3ec\ud568 \ud3ec\ud568 \ud3ec\ud568 \ud3ec\ud568 \ud3ec\ud568 \ud3ec\ud568 \ud3ec\ud568 \ud3ec\ud568 \ud3ec\ud568 \ud3ec\ud568 \ud3ec\ud568 \ud3ec\ud568 \ud3ec\ud568 \ud3ec\ud568 \ud3ec\ud568 \ud3ec\ud568 \ud3ec\ud568 \ud3ec\ud568 \ud3ec\ud568 \ud3ec\ud568 \ud3ec\ud568 \ud3ec\ud568 \ud3ec\ud568 \ud3ec\ud568 \ud3ec\ud568 \ud3ec\ud568 \ud3ec\ud568 \ud3ec\ud568 \ud3ec\ud568 \ud3ec\ud568 \ud3ec\ud568 \ud3ec\ud568 \ud3ec\ud568 \ud3ec\ud568 \ud3ec\ud568 \ud3ec\ud568 \ud3ec\ud568 \ud3ec\ud568 \ud3ec\ud568 \ud3ec\ud568 \ud3ec\ud568 \ud3ec\ud568 \ud3ec\ud568 \ud3ec\ud568 \ud3ec\ud568 \ud3ec\ud568 \ud3ec\ud568 \ud3ec\ud568 \ud3ec\ud568 \ud3ec\ud568 \ud3ec\ud568 \ud3ec\ud568 \ud3ec\ud568 \ud3ec\ud568 \ud3ec\ud568 \ud3ec\ud568 \ud3ec\ud568 \ud3ec\ud568 \ud3ec\ud568 \ud3ec\ud568 \ud3ec\ud568 \ud3ec\ud568 \ud3ec\ud568 \ud3ec\ud568 \ud3ec\ud568 \ud3ec\ud568 \ud3ec\ud568 \ud3ec\ud568 \ud3ec\ud568 \ud3ec\ud568 \ud3ec\ud568 \ud3ec\ud568 \ud3ec\ud568 \ud3ec\ud568 \ud3ec\ud568 \ud3ec\ud568 \ud3ec\ud568 \ud3ec\ud568 \ud3ec\ud568 \ud3ec\ud568 \ud3ec\ud568 \ud3ec\ud568 \ud3ec\ud568 \ud3ec\ud568 \ud3ec\ud568 \ud3ec\ud568 \ud3ec\ud568 \ud3ec\ud568 \ud3ec\ud568 \ud3ec\ud568 \ud3ec\ud568 \ud3ec\ud568 \ud3ec\ud568 \ud3ec\ud568 \ud3ec\ud568 \ud3ec\ud568 \ud3ec\ud568 \ud3ec\ud568 \ud3ec\ud568 \ud3ec\ud568 \ud3ec\ud568 \ud3ec\ud568 \ud3ec\ud568 \ud3ec\ud568 \ud3ec\ud568 \ud3ec\ud568 \ud3ec\ud568 \ud3ec\ud568 \ud3ec\ud568 \ud3ec\ud568 \ud3ec\ud568 \ud3ec\ud568 \ud3ec\ud568 \ud3ec\ud568 \ud3ec\ud568 \ud3ec\ud568 \ud3ec\ud568 \ud3ec\ud568 \ud3ec\ud568 \ud3ec\ud568 \ud3ec\ud568 \ud3ec\ud568 \ud3ec\ud568 \ud3ec\ud568 \ud3ec\ud568 \ud3ec\ud568 \ud3ec\ud568 \ud3ec\ud568 \ud3ec\ud568 \ud3ec\ud568 \ud3ec\ud568 \ud3ec\ud568 \ud3ec\ud568 \ud3ec\ud568 \ud3ec\ud568 \ud3ec\ud568 \ud3ec\ud568 \ud3ec\ud568 \ud3ec\ud568 \ud3ec\ud568 \ud3ec\ud568 \ud3ec\ud568 \ud3ec\ud568 \ud3ec\ud568 \ud3ec\ud568 \ud3ec\ud568 \ud3ec\ud568 \ud3ec\ud568 \ud3ec\ud568 \ud3ec\ud568 \ud3ec\ud568 \ud3ec\ud568 \ud3ec\ud568 \ud3ec\ud568 \ud3ec\ud568 \ud3ec\ud568 \ud3ec\ud568 \ud3ec\ud568 \ud3ec\ud568 \ud3ec\ud568 \ud3ec\ud568 \ud3ec\ud568 \ud3ec\ud568 \ud3ec\ud568 \ud3ec\ud568 \ud3ec\ud568 \ud3ec\ud568 \ud3ec\ud568 \ud3ec\ud568 \ud3ec\ud568 \ud3ec\ud568 \ud3ec\ud568 \ud3ec\ud568 \ud3ec\ud568 \ud3ec\ud568 \ud3ec\ud568 \ud3ec\ud568 \ud3ec\ud568 \ud3ec\ud568 \ud3ec\ud568 \ud3ec\ud568 \ud3ec\ud568 \ud3ec\ud568 \ud3ec\ud568 \ud3ec\ud568 \ud3ec\ud568 \ud3ec\ud568 \ud3ec\ud568 \ud3ec\ud568 \ud3ec\ud568 \ud3ec\ud568 \ud3ec\ud568 \ud3ec\ud568 \ud3ec\ud568 \ud3ec\ud568 \ud3ec\ud568 \ud3ec\ud568 \ud3ec\ud568 \ud3ec\ud568 \ud3ec\ud568 \ud3ec\ud568 \ud3ec\ud568 \ud3ec\ud568 \ud3ec\ud568 \ud3ec\ud568 \ud3ec\ud568 \ud3ec\ud568 \ud3ec\ud568 \ud3ec\ud568 \ud3ec\ud568 \ud3ec\ud568 \ud3ec\ud568 \ud3ec\ud568 \ud3ec\ud568 \ud3ec\ud568 \ud3ec\ud568 \ud3ec\ud568 \ud3ec\ud568 \ud3ec\ud568 \ud3ec\ud568"
    },
    {
        "question": "What is the label of the research department?",
        "query": "SELECT ?label WHERE { :researchDep rdfs:label ?label . }",
        "generated": "\uc81c\uacf5 \uc81c\uacf5 \uc81c\uacf5 \uc81c\uacf5 \uc81c\uacf5 \uc81c\uacf5 \uc81c\uacf5 \uc81c\uacf5 \uc81c\uacf5 \uc81c\uacf5 \uc81c\uacf5 \uc81c\uacf5 \uc81c\uacf5 \uc81c\uacf5 \uc81c\uacf5 \uc81c\uacf5 \uc81c\uacf5 \uc81c\uacf5 \uc81c\uacf5 \uc81c\uacf5 \uc81c\uacf5 \uc81c\uacf5 \uc81c\uacf5 \uc81c\uacf5 \uc81c\uacf5 \uc81c\uacf5 \uc81c\uacf5 \uc81c\uacf5 \uc81c\uacf5 \uc81c\uacf5 \uc81c\uacf5 \uc81c\uacf5 \uc81c\uacf5 \uc81c\uacf5 \uc81c\uacf5 \uc81c\uacf5 \uc81c\uacf5 \uc81c\uacf5 \uc81c\uacf5 \uc81c\uacf5 \uc81c\uacf5 \uc81c\uacf5 \uc81c\uacf5 \uc81c\uacf5 \uc81c\uacf5 \uc81c\uacf5 \uc81c\uacf5 \uc81c\uacf5 \uc81c\uacf5 \uc81c\uacf5 \uc81c\uacf5 \uc81c\uacf5 \uc81c\uacf5 \uc81c\uacf5 \uc81c\uacf5 \uc81c\uacf5 \uc81c\uacf5 \uc81c\uacf5 \uc81c\uacf5 \uc81c\uacf5 \uc81c\uacf5 \uc81c\uacf5 \uc81c\uacf5 \uc81c\uacf5 \uc81c\uacf5 \uc81c\uacf5 \uc81c\uacf5 \uc81c\uacf5 \uc81c\uacf5 \uc81c\uacf5 \uc81c\uacf5 \uc81c\uacf5 \uc81c\uacf5 \uc81c\uacf5 \uc81c\uacf5 \uc81c\uacf5 \uc81c\uacf5 \uc81c\uacf5 \uc81c\uacf5 \uc81c\uacf5 \uc81c\uacf5 \uc81c\uacf5 \uc81c\uacf5 \uc81c\uacf5 \uc81c\uacf5 \uc81c\uacf5 \uc81c\uacf5 \uc81c\uacf5 \uc81c\uacf5 \uc81c\uacf5 \uc81c\uacf5 \uc81c\uacf5 \uc81c\uacf5 \uc81c\uacf5 \uc81c\uacf5 \uc81c\uacf5 \uc81c\uacf5 \uc81c\uacf5 \uc81c\uacf5 \uc81c\uacf5 \uc81c\uacf5 \uc81c\uacf5 \uc81c\uacf5 \uc81c\uacf5 \uc81c\uacf5 \uc81c\uacf5 \uc81c\uacf5 \uc81c\uacf5 \uc81c\uacf5 \uc81c\uacf5 \uc81c\uacf5 \uc81c\uacf5 \uc81c\uacf5 \uc81c\uacf5 \uc81c\uacf5 \uc81c\uacf5 \uc81c\uacf5 \uc81c\uacf5 \uc81c\uacf5 \uc81c\uacf5 \uc81c\uacf5 \uc81c\uacf5 \uc81c\uacf5 \uc81c\uacf5 \uc81c\uacf5 \uc81c\uacf5 \uc81c\uacf5 \uc81c\uacf5 \uc81c\uacf5 \uc81c\uacf5 \uc81c\uacf5 \uc81c\uacf5 \uc81c\uacf5 \uc81c\uacf5 \uc81c\uacf5 \uc81c\uacf5 \uc81c\uacf5 \uc81c\uacf5 \uc81c\uacf5 \uc81c\uacf5 \uc81c\uacf5 \uc81c\uacf5 \uc81c\uacf5 \uc81c\uacf5 \uc81c\uacf5 \uc81c\uacf5 \uc81c\uacf5 \uc81c\uacf5 \uc81c\uacf5 \uc81c\uacf5 \uc81c\uacf5 \uc81c\uacf5 \uc81c\uacf5 \uc81c\uacf5 \uc81c\uacf5 \uc81c\uacf5 \uc81c\uacf5 \uc81c\uacf5 \uc81c\uacf5 \uc81c\uacf5 \uc81c\uacf5 \uc81c\uacf5 \uc81c\uacf5 \uc81c\uacf5 \uc81c\uacf5 \uc81c\uacf5 \uc81c\uacf5 \uc81c\uacf5 \uc81c\uacf5 \uc81c\uacf5 \uc81c\uacf5 \uc81c\uacf5 \uc81c\uacf5 \uc81c\uacf5 \uc81c\uacf5 \uc81c\uacf5 \uc81c\uacf5 \uc81c\uacf5 \uc81c\uacf5 \uc81c\uacf5 \uc81c\uacf5 \uc81c\uacf5 \uc81c\uacf5 \uc81c\uacf5 \uc81c\uacf5 \uc81c\uacf5 \uc81c\uacf5 \uc81c\uacf5 \uc81c\uacf5 \uc81c\uacf5 \uc81c\uacf5 \uc81c\uacf5 \uc81c\uacf5 \uc81c\uacf5 \uc81c\uacf5 \uc81c\uacf5 \uc81c\uacf5 \uc81c\uacf5 \uc81c\uacf5 \uc81c\uacf5 \uc81c\uacf5 \uc81c\uacf5 \uc81c\uacf5 \uc81c\uacf5 \uc81c\uacf5 \uc81c\uacf5 \uc81c\uacf5 \uc81c\uacf5 \uc81c\uacf5 \uc81c\uacf5 \uc81c\uacf5 \uc81c\uacf5 \uc81c\uacf5 \uc81c\uacf5 \uc81c\uacf5 \uc81c\uacf5 \uc81c\uacf5 \uc81c\uacf5 \uc81c\uacf5 \uc81c\uacf5 \uc81c\uacf5 \uc81c\uacf5 \uc81c\uacf5 \uc81c\uacf5 \uc81c\uacf5 \uc81c\uacf5 \uc81c\uacf5 \uc81c\uacf5 \uc81c\uacf5 \uc81c\uacf5 \uc81c\uacf5 \uc81c\uacf5 \uc81c\uacf5 \uc81c\uacf5 \uc81c\uacf5 \uc81c\uacf5 \uc81c\uacf5 \uc81c\uacf5 \uc81c\uacf5 \uc81c\uacf5 \uc81c\uacf5 \uc81c\uacf5 \uc81c\uacf5 \uc81c\uacf5 \uc81c\uacf5 \uc81c\uacf5 \uc81c\uacf5 \uc81c\uacf5 \uc81c\uacf5 \uc81c\uacf5 \uc81c\uacf5 \uc81c\uacf5 \uc81c\uacf5 \uc81c\uacf5 \uc81c\uacf5"
    },
    {
        "question": "What is the label of the marketing department?",
        "query": "SELECT ?label WHERE { :marketingDep rdfs:label ?label . }",
        "generated": "\ud65c\uc6a9 \ud65c\uc6a9 \ud65c\uc6a9 \ud65c\uc6a9 \ud65c\uc6a9 \ud65c\uc6a9 \ud65c\uc6a9 \ud65c\uc6a9 \ud65c\uc6a9 \ud65c\uc6a9 \ud65c\uc6a9 \ud65c\uc6a9 \ud65c\uc6a9 \ud65c\uc6a9 \ud65c\uc6a9 \ud65c\uc6a9 \ud65c\uc6a9 \ud65c\uc6a9 \ud65c\uc6a9 \ud65c\uc6a9 \ud65c\uc6a9 \ud65c\uc6a9 \ud65c\uc6a9 \ud65c\uc6a9 \ud65c\uc6a9 \ud65c\uc6a9 \ud65c\uc6a9 \ud65c\uc6a9 \ud65c\uc6a9 \ud65c\uc6a9 \ud65c\uc6a9 \ud65c\uc6a9 \ud65c\uc6a9 \ud65c\uc6a9 \ud65c\uc6a9 \ud65c\uc6a9 \ud65c\uc6a9 \ud65c\uc6a9 \ud65c\uc6a9 \ud65c\uc6a9 \ud65c\uc6a9 \ud65c\uc6a9 \ud65c\uc6a9 \ud65c\uc6a9 \ud65c\uc6a9 \ud65c\uc6a9 \ud65c\uc6a9 \ud65c\uc6a9 \ud65c\uc6a9 \ud65c\uc6a9 \ud65c\uc6a9 \ud65c\uc6a9 \ud65c\uc6a9 \ud65c\uc6a9 \ud65c\uc6a9 \ud65c\uc6a9 \ud65c\uc6a9 \ud65c\uc6a9 \ud65c\uc6a9 \ud65c\uc6a9 \ud65c\uc6a9 \ud65c\uc6a9 \ud65c\uc6a9 \ud65c\uc6a9 \ud65c\uc6a9 \ud65c\uc6a9 \ud65c\uc6a9 \ud65c\uc6a9 \ud65c\uc6a9 \ud65c\uc6a9 \ud65c\uc6a9 \ud65c\uc6a9 \ud65c\uc6a9 \ud65c\uc6a9 \ud65c\uc6a9 \ud65c\uc6a9 \ud65c\uc6a9 \ud65c\uc6a9 \ud65c\uc6a9 \ud65c\uc6a9 \ud65c\uc6a9 \ud65c\uc6a9 \ud65c\uc6a9 \ud65c\uc6a9 \ud65c\uc6a9 \ud65c\uc6a9 \ud65c\uc6a9 \ud65c\uc6a9 \ud65c\uc6a9 \ud65c\uc6a9 \ud65c\uc6a9 \ud65c\uc6a9 \ud65c\uc6a9 \ud65c\uc6a9 \ud65c\uc6a9 \ud65c\uc6a9 \ud65c\uc6a9 \ud65c\uc6a9 \ud65c\uc6a9 \ud65c\uc6a9 \ud65c\uc6a9 \ud65c\uc6a9 \ud65c\uc6a9 \ud65c\uc6a9 \ud65c\uc6a9 \ud65c\uc6a9 \ud65c\uc6a9 \ud65c\uc6a9 \ud65c\uc6a9 \ud65c\uc6a9 \ud65c\uc6a9 \ud65c\uc6a9 \ud65c\uc6a9 \ud65c\uc6a9 \ud65c\uc6a9 \ud65c\uc6a9 \ud65c\uc6a9 \ud65c\uc6a9 \ud65c\uc6a9 \ud65c\uc6a9 \ud65c\uc6a9 \ud65c\uc6a9 \ud65c\uc6a9 \ud65c\uc6a9 \ud65c\uc6a9 \ud65c\uc6a9 \ud65c\uc6a9 \ud65c\uc6a9 \ud65c\uc6a9 \ud65c\uc6a9 \ud65c\uc6a9 \ud65c\uc6a9 \ud65c\uc6a9 \ud65c\uc6a9 \ud65c\uc6a9 \ud65c\uc6a9 \ud65c\uc6a9 \ud65c\uc6a9 \ud65c\uc6a9 \ud65c\uc6a9 \ud65c\uc6a9 \ud65c\uc6a9 \ud65c\uc6a9 \ud65c\uc6a9 \ud65c\uc6a9 \ud65c\uc6a9 \ud65c\uc6a9 \ud65c\uc6a9 \ud65c\uc6a9 \ud65c\uc6a9 \ud65c\uc6a9 \ud65c\uc6a9 \ud65c\uc6a9 \ud65c\uc6a9 \ud65c\uc6a9 \ud65c\uc6a9 \ud65c\uc6a9 \ud65c\uc6a9 \ud65c\uc6a9 \ud65c\uc6a9 \ud65c\uc6a9 \ud65c\uc6a9 \ud65c\uc6a9 \ud65c\uc6a9 \ud65c\uc6a9 \ud65c\uc6a9 \ud65c\uc6a9 \ud65c\uc6a9 \ud65c\uc6a9 \ud65c\uc6a9 \ud65c\uc6a9 \ud65c\uc6a9 \ud65c\uc6a9 \ud65c\uc6a9 \ud65c\uc6a9 \ud65c\uc6a9 \ud65c\uc6a9 \ud65c\uc6a9 \ud65c\uc6a9 \ud65c\uc6a9 \ud65c\uc6a9 \ud65c\uc6a9 \ud65c\uc6a9 \ud65c\uc6a9 \ud65c\uc6a9 \ud65c\uc6a9 \ud65c\uc6a9 \ud65c\uc6a9 \ud65c\uc6a9 \ud65c\uc6a9 \ud65c\uc6a9 \ud65c\uc6a9 \ud65c\uc6a9 \ud65c\uc6a9 \ud65c\uc6a9 \ud65c\uc6a9 \ud65c\uc6a9 \ud65c\uc6a9 \ud65c\uc6a9 \ud65c\uc6a9 \ud65c\uc6a9 \ud65c\uc6a9 \ud65c\uc6a9 \ud65c\uc6a9 \ud65c\uc6a9 \ud65c\uc6a9 \ud65c\uc6a9 \ud65c\uc6a9 \ud65c\uc6a9 \ud65c\uc6a9 \ud65c\uc6a9 \ud65c\uc6a9 \ud65c\uc6a9 \ud65c\uc6a9 \ud65c\uc6a9 \ud65c\uc6a9 \ud65c\uc6a9 \ud65c\uc6a9 \ud65c\uc6a9 \ud65c\uc6a9 \ud65c\uc6a9 \ud65c\uc6a9 \ud65c\uc6a9 \ud65c\uc6a9 \ud65c\uc6a9 \ud65c\uc6a9 \ud65c\uc6a9 \ud65c\uc6a9 \ud65c\uc6a9 \ud65c\uc6a9 \ud65c\uc6a9 \ud65c\uc6a9 \ud65c\uc6a9 \ud65c\uc6a9 \ud65c\uc6a9 \ud65c\uc6a9 \ud65c\uc6a9 \ud65c\uc6a9 \ud65c\uc6a9 \ud65c\uc6a9 \ud65c\uc6a9 \ud65c\uc6a9 \ud65c\uc6a9 \ud65c\uc6a9 \ud65c\uc6a9 \ud65c\uc6a9 \ud65c\uc6a9 \ud65c\uc6a9 \ud65c\uc6a9 \ud65c\uc6a9 \ud65c\uc6a9 \ud65c\uc6a9 \ud65c\uc6a9 \ud65c\uc6a9 \ud65c\uc6a9"
    },
    {
        "question": "Who is the member of the research department as the chief research officer?",
        "query": "SELECT ?member WHERE { [ org:member ?member ; org:organization :researchDep ; org:role :chiefResearchOfficer ] . }",
        "generated": "\ud3ec\ud568 \ud3ec\ud568 \ud3ec\ud568 \ud3ec\ud568 \ud3ec\ud568 \ud3ec\ud568 \ud3ec\ud568 \ud3ec\ud568 \ud3ec\ud568 \ud3ec\ud568 \ud3ec\ud568 \ud3ec\ud568 \ud3ec\ud568 \ud3ec\ud568 \ud3ec\ud568 \ud3ec\ud568 \ud3ec\ud568 \ud3ec\ud568 \ud3ec\ud568 \ud3ec\ud568 \ud3ec\ud568 \ud3ec\ud568 \ud3ec\ud568 \ud3ec\ud568 \ud3ec\ud568 \ud3ec\ud568 \ud3ec\ud568 \ud3ec\ud568 \ud3ec\ud568 \ud3ec\ud568 \ud3ec\ud568 \ud3ec\ud568 \ud3ec\ud568 \ud3ec\ud568 \ud3ec\ud568 \ud3ec\ud568 \ud3ec\ud568 \ud3ec\ud568 \ud3ec\ud568 \ud3ec\ud568 \ud3ec\ud568 \ud3ec\ud568 \ud3ec\ud568 \ud3ec\ud568 \ud3ec\ud568 \ud3ec\ud568 \ud3ec\ud568 \ud3ec\ud568 \ud3ec\ud568 \ud3ec\ud568 \ud3ec\ud568 \ud3ec\ud568 \ud3ec\ud568 \ud3ec\ud568 \ud3ec\ud568 \ud3ec\ud568 \ud3ec\ud568 \ud3ec\ud568 \ud3ec\ud568 \ud3ec\ud568 \ud3ec\ud568 \ud3ec\ud568 \ud3ec\ud568 \ud3ec\ud568 \ud3ec\ud568 \ud3ec\ud568 \ud3ec\ud568 \ud3ec\ud568 \ud3ec\ud568 \ud3ec\ud568 \ud3ec\ud568 \ud3ec\ud568 \ud3ec\ud568 \ud3ec\ud568 \ud3ec\ud568 \ud3ec\ud568 \ud3ec\ud568 \ud3ec\ud568 \ud3ec\ud568 \ud3ec\ud568 \ud3ec\ud568 \ud3ec\ud568 \ud3ec\ud568 \ud3ec\ud568 \ud3ec\ud568 \ud3ec\ud568 \ud3ec\ud568 \ud3ec\ud568 \ud3ec\ud568 \ud3ec\ud568 \ud3ec\ud568 \ud3ec\ud568 \ud3ec\ud568 \ud3ec\ud568 \ud3ec\ud568 \ud3ec\ud568 \ud3ec\ud568 \ud3ec\ud568 \ud3ec\ud568 \ud3ec\ud568 \ud3ec\ud568 \ud3ec\ud568 \ud3ec\ud568 \ud3ec\ud568 \ud3ec\ud568 \ud3ec\ud568 \ud3ec\ud568 \ud3ec\ud568 \ud3ec\ud568 \ud3ec\ud568 \ud3ec\ud568 \ud3ec\ud568 \ud3ec\ud568 \ud3ec\ud568 \ud3ec\ud568 \ud3ec\ud568 \ud3ec\ud568 \ud3ec\ud568 \ud3ec\ud568 \ud3ec\ud568 \ud3ec\ud568 \ud3ec\ud568 \ud3ec\ud568 \ud3ec\ud568 \ud3ec\ud568 \ud3ec\ud568 \ud3ec\ud568 \ud3ec\ud568 \ud3ec\ud568 \ud3ec\ud568 \ud3ec\ud568 \ud3ec\ud568 \ud3ec\ud568 \ud3ec\ud568 \ud3ec\ud568 \ud3ec\ud568 \ud3ec\ud568 \ud3ec\ud568 \ud3ec\ud568 \ud3ec\ud568 \ud3ec\ud568 \ud3ec\ud568 \ud3ec\ud568 \ud3ec\ud568 \ud3ec\ud568 \ud3ec\ud568 \ud3ec\ud568 \ud3ec\ud568 \ud3ec\ud568 \ud3ec\ud568 \ud3ec\ud568 \ud3ec\ud568 \ud3ec\ud568 \ud3ec\ud568 \ud3ec\ud568 \ud3ec\ud568 \ud3ec\ud568 \ud3ec\ud568 \ud3ec\ud568 \ud3ec\ud568 \ud3ec\ud568 \ud3ec\ud568 \ud3ec\ud568 \ud3ec\ud568 \ud3ec\ud568 \ud3ec\ud568 \ud3ec\ud568 \ud3ec\ud568 \ud3ec\ud568 \ud3ec\ud568 \ud3ec\ud568 \ud3ec\ud568 \ud3ec\ud568 \ud3ec\ud568 \ud3ec\ud568 \ud3ec\ud568 \ud3ec\ud568 \ud3ec\ud568 \ud3ec\ud568 \ud3ec\ud568 \ud3ec\ud568 \ud3ec\ud568 \ud3ec\ud568 \ud3ec\ud568 \ud3ec\ud568 \ud3ec\ud568 \ud3ec\ud568 \ud3ec\ud568 \ud3ec\ud568 \ud3ec\ud568 \ud3ec\ud568 \ud3ec\ud568 \ud3ec\ud568 \ud3ec\ud568 \ud3ec\ud568 \ud3ec\ud568 \ud3ec\ud568 \ud3ec\ud568 \ud3ec\ud568 \ud3ec\ud568 \ud3ec\ud568 \ud3ec\ud568 \ud3ec\ud568 \ud3ec\ud568 \ud3ec\ud568 \ud3ec\ud568 \ud3ec\ud568 \ud3ec\ud568 \ud3ec\ud568 \ud3ec\ud568 \ud3ec\ud568 \ud3ec\ud568 \ud3ec\ud568 \ud3ec\ud568 \ud3ec\ud568 \ud3ec\ud568 \ud3ec\ud568 \ud3ec\ud568 \ud3ec\ud568 \ud3ec\ud568 \ud3ec\ud568 \ud3ec\ud568 \ud3ec\ud568 \ud3ec\ud568 \ud3ec\ud568 \ud3ec\ud568 \ud3ec\ud568 \ud3ec\ud568 \ud3ec\ud568 \ud3ec\ud568 \ud3ec\ud568 \ud3ec\ud568 \ud3ec\ud568 \ud3ec\ud568 \ud3ec\ud568 \ud3ec\ud568 \ud3ec\ud568 \ud3ec\ud568 \ud3ec\ud568 \ud3ec\ud568 \ud3ec\ud568 \ud3ec\ud568 \ud3ec\ud568 \ud3ec\ud568 \ud3ec\ud568 \ud3ec\ud568 \ud3ec\ud568 \ud3ec\ud568 \ud3ec\ud568 \ud3ec\ud568 \ud3ec\ud568 \ud3ec\ud568 \ud3ec\ud568 \ud3ec\ud568 \ud3ec\ud568"
    },
    {
        "question": "Who is the member of the marketing department as the marketing manager?",
        "query": "SELECT ?member WHERE { [ org:member ?member ; org:organization :marketingDep ; org:role :marketingManager ] . }",
        "generated": "\ucc3e\ucc3e\ucc3e\ucc3e\ucc3e\ucc3e\ucc3e\ucc3e\ucc3e\ucc3e\ucc3e\ucc3e\ucc3e\ucc3e\ucc3e\ucc3e\ucc3e\ucc3e\ucc3e\ucc3e\ucc3e\ucc3e\ucc3e\ucc3e\ucc3e\ucc3e\ucc3e\ucc3e\ucc3e\ucc3e\ucc3e\ucc3e\ucc3e\ucc3e\ucc3e\ucc3e\ucc3e\ucc3e\ucc3e\ucc3e\ucc3e\ucc3e\ucc3e\ucc3e\ucc3e\ucc3e\ucc3e\ucc3e\ucc3e\ucc3e\ucc3e\ucc3e\ucc3e\ucc3e\ucc3e\ucc3e\ucc3e\ucc3e\ucc3e\ucc3e\ucc3e\ucc3e\ucc3e\ucc3e\ucc3e\ucc3e\ucc3e\ucc3e\ucc3e\ucc3e\ucc3e\ucc3e\ucc3e\ucc3e\ucc3e\ucc3e\ucc3e\ucc3e\ucc3e\ucc3e\ucc3e\ucc3e\ucc3e\ucc3e\ucc3e\ucc3e\ucc3e\ucc3e\ucc3e\ucc3e\ucc3e\ucc3e\ucc3e\ucc3e\ucc3e\ucc3e\ucc3e\ucc3e\ucc3e\ucc3e\ucc3e\ucc3e\ucc3e\ucc3e\ucc3e\ucc3e\ucc3e\ucc3e\ucc3e\ucc3e\ucc3e\ucc3e\ucc3e\ucc3e\ucc3e\ucc3e\ucc3e\ucc3e\ucc3e\ucc3e\ucc3e\ucc3e\ucc3e\ucc3e\ucc3e\ucc3e\ucc3e\ucc3e\ucc3e\ucc3e\ucc3e\ucc3e\ucc3e\ucc3e\ucc3e\ucc3e\ucc3e\ucc3e\ucc3e\ucc3e\ucc3e\ucc3e\ucc3e\ucc3e\ucc3e\ucc3e\ucc3e\ucc3e\ucc3e\ucc3e\ucc3e\ucc3e\ucc3e\ucc3e\ucc3e\ucc3e\ucc3e\ucc3e\ucc3e\ucc3e\ucc3e\ucc3e\ucc3e\ucc3e\ucc3e\ucc3e\ucc3e\ucc3e\ucc3e\ucc3e\ucc3e\ucc3e\ucc3e\ucc3e\ucc3e\ucc3e\ucc3e\ucc3e\ucc3e\ucc3e\ucc3e\ucc3e\ucc3e\ucc3e\ucc3e\ucc3e\ucc3e\ucc3e\ucc3e\ucc3e\ucc3e\ucc3e\ucc3e\ucc3e\ucc3e\ucc3e\ucc3e\ucc3e\ucc3e\ucc3e\ucc3e\ucc3e\ucc3e\ucc3e\ucc3e\ucc3e\ucc3e\ucc3e\ucc3e\ucc3e\ucc3e\ucc3e\ucc3e\ucc3e\ucc3e\ucc3e\ucc3e\ucc3e\ucc3e\ucc3e\ucc3e\ucc3e\ucc3e\ucc3e\ucc3e\ucc3e\ucc3e\ucc3e\ucc3e\ucc3e\ucc3e\ucc3e\ucc3e\ucc3e\ucc3e\ucc3e\ucc3e\ucc3e\ucc3e\ucc3e\ucc3e\ucc3e\ucc3e\ucc3e\ucc3e\ucc3e\ucc3e\ucc3e\ucc3e\ucc3e\ucc3e\ucc3e\ucc3e\ucc3e\ucc3e"
    },
    {
        "question": "How many persons exist in the graph?",
        "query": "SELECT (count(?person) as ?count) WHERE { ?person a foaf:Person . }",
        "generated": "\ud65c\uc6a9 \ud65c\uc6a9 \ud65c\uc6a9 \ud65c\uc6a9 \ud65c\uc6a9 \ud65c\uc6a9 \ud65c\uc6a9 \ud65c\uc6a9 \ud65c\uc6a9 \ud65c\uc6a9 \ud65c\uc6a9 \ud65c\uc6a9 \ud65c\uc6a9 \ud65c\uc6a9 \ud65c\uc6a9 \ud65c\uc6a9 \ud65c\uc6a9 \ud65c\uc6a9 \ud65c\uc6a9 \ud65c\uc6a9 \ud65c\uc6a9 \ud65c\uc6a9 \ud65c\uc6a9 \ud65c\uc6a9 \ud65c\uc6a9 \ud65c\uc6a9 \ud65c\uc6a9 \ud65c\uc6a9 \ud65c\uc6a9 \ud65c\uc6a9 \ud65c\uc6a9 \ud65c\uc6a9 \ud65c\uc6a9 \ud65c\uc6a9 \ud65c\uc6a9 \ud65c\uc6a9 \ud65c\uc6a9 \ud65c\uc6a9 \ud65c\uc6a9 \ud65c\uc6a9 \ud65c\uc6a9 \ud65c\uc6a9 \ud65c\uc6a9 \ud65c\uc6a9 \ud65c\uc6a9 \ud65c\uc6a9 \ud65c\uc6a9 \ud65c\uc6a9 \ud65c\uc6a9 \ud65c\uc6a9 \ud65c\uc6a9 \ud65c\uc6a9 \ud65c\uc6a9 \ud65c\uc6a9 \ud65c\uc6a9 \ud65c\uc6a9 \ud65c\uc6a9 \ud65c\uc6a9 \ud65c\uc6a9 \ud65c\uc6a9 \ud65c\uc6a9 \ud65c\uc6a9 \ud65c\uc6a9 \ud65c\uc6a9 \ud65c\uc6a9 \ud65c\uc6a9 \ud65c\uc6a9 \ud65c\uc6a9 \ud65c\uc6a9 \ud65c\uc6a9 \ud65c\uc6a9 \ud65c\uc6a9 \ud65c\uc6a9 \ud65c\uc6a9 \ud65c\uc6a9 \ud65c\uc6a9 \ud65c\uc6a9 \ud65c\uc6a9 \ud65c\uc6a9 \ud65c\uc6a9 \ud65c\uc6a9 \ud65c\uc6a9 \ud65c\uc6a9 \ud65c\uc6a9 \ud65c\uc6a9 \ud65c\uc6a9 \ud65c\uc6a9 \ud65c\uc6a9 \ud65c\uc6a9 \ud65c\uc6a9 \ud65c\uc6a9 \ud65c\uc6a9 \ud65c\uc6a9 \ud65c\uc6a9 \ud65c\uc6a9 \ud65c\uc6a9 \ud65c\uc6a9 \ud65c\uc6a9 \ud65c\uc6a9 \ud65c\uc6a9 \ud65c\uc6a9 \ud65c\uc6a9 \ud65c\uc6a9 \ud65c\uc6a9 \ud65c\uc6a9 \ud65c\uc6a9 \ud65c\uc6a9 \ud65c\uc6a9 \ud65c\uc6a9 \ud65c\uc6a9 \ud65c\uc6a9 \ud65c\uc6a9 \ud65c\uc6a9 \ud65c\uc6a9 \ud65c\uc6a9 \ud65c\uc6a9 \ud65c\uc6a9 \ud65c\uc6a9 \ud65c\uc6a9 \ud65c\uc6a9 \ud65c\uc6a9 \ud65c\uc6a9 \ud65c\uc6a9 \ud65c\uc6a9 \ud65c\uc6a9 \ud65c\uc6a9 \ud65c\uc6a9 \ud65c\uc6a9 \ud65c\uc6a9 \ud65c\uc6a9 \ud65c\uc6a9 \ud65c\uc6a9 \ud65c\uc6a9 \ud65c\uc6a9 \ud65c\uc6a9 \ud65c\uc6a9 \ud65c\uc6a9 \ud65c\uc6a9 \ud65c\uc6a9 \ud65c\uc6a9 \ud65c\uc6a9 \ud65c\uc6a9 \ud65c\uc6a9 \ud65c\uc6a9 \ud65c\uc6a9 \ud65c\uc6a9 \ud65c\uc6a9 \ud65c\uc6a9 \ud65c\uc6a9 \ud65c\uc6a9 \ud65c\uc6a9 \ud65c\uc6a9 \ud65c\uc6a9 \ud65c\uc6a9 \ud65c\uc6a9 \ud65c\uc6a9 \ud65c\uc6a9 \ud65c\uc6a9 \ud65c\uc6a9 \ud65c\uc6a9 \ud65c\uc6a9 \ud65c\uc6a9 \ud65c\uc6a9 \ud65c\uc6a9 \ud65c\uc6a9 \ud65c\uc6a9 \ud65c\uc6a9 \ud65c\uc6a9 \ud65c\uc6a9 \ud65c\uc6a9 \ud65c\uc6a9 \ud65c\uc6a9 \ud65c\uc6a9 \ud65c\uc6a9 \ud65c\uc6a9 \ud65c\uc6a9 \ud65c\uc6a9 \ud65c\uc6a9 \ud65c\uc6a9 \ud65c\uc6a9 \ud65c\uc6a9 \ud65c\uc6a9 \ud65c\uc6a9 \ud65c\uc6a9 \ud65c\uc6a9 \ud65c\uc6a9 \ud65c\uc6a9 \ud65c\uc6a9 \ud65c\uc6a9 \ud65c\uc6a9 \ud65c\uc6a9 \ud65c\uc6a9 \ud65c\uc6a9 \ud65c\uc6a9 \ud65c\uc6a9 \ud65c\uc6a9 \ud65c\uc6a9 \ud65c\uc6a9 \ud65c\uc6a9 \ud65c\uc6a9 \ud65c\uc6a9 \ud65c\uc6a9 \ud65c\uc6a9 \ud65c\uc6a9 \ud65c\uc6a9 \ud65c\uc6a9 \ud65c\uc6a9 \ud65c\uc6a9 \ud65c\uc6a9 \ud65c\uc6a9 \ud65c\uc6a9 \ud65c\uc6a9 \ud65c\uc6a9 \ud65c\uc6a9 \ud65c\uc6a9 \ud65c\uc6a9 \ud65c\uc6a9 \ud65c\uc6a9 \ud65c\uc6a9 \ud65c\uc6a9 \ud65c\uc6a9 \ud65c\uc6a9 \ud65c\uc6a9 \ud65c\uc6a9 \ud65c\uc6a9 \ud65c\uc6a9 \ud65c\uc6a9 \ud65c\uc6a9 \ud65c\uc6a9 \ud65c\uc6a9 \ud65c\uc6a9 \ud65c\uc6a9 \ud65c\uc6a9 \ud65c\uc6a9 \ud65c\uc6a9 \ud65c\uc6a9 \ud65c\uc6a9 \ud65c\uc6a9 \ud65c\uc6a9 \ud65c\uc6a9 \ud65c\uc6a9 \ud65c\uc6a9 \ud65c\uc6a9 \ud65c\uc6a9 \ud65c\uc6a9 \ud65c\uc6a9 \ud65c\uc6a9 \ud65c\uc6a9 \ud65c\uc6a9 \ud65c\uc6a9 \ud65c\uc6a9 \ud65c\uc6a9 \ud65c\uc6a9 \ud65c\uc6a9 \ud65c\uc6a9"
    },
    {
        "question": "How many organizational units exist in the graph?",
        "query": "SELECT (count(?organizationalUnit) as ?count) WHERE { ?organizationalUnit a org:OrganizationalUnit . }",
        "generated": "\ud65c\uc6a9 \ud65c\uc6a9 \ud65c\uc6a9 \ud65c\uc6a9 \ud65c\uc6a9 \ud65c\uc6a9 \ud65c\uc6a9 \ud65c\uc6a9 \ud65c\uc6a9 \ud65c\uc6a9 \ud65c\uc6a9 \ud65c\uc6a9 \ud65c\uc6a9 \ud65c\uc6a9 \ud65c\uc6a9 \ud65c\uc6a9 \ud65c\uc6a9 \ud65c\uc6a9 \ud65c\uc6a9 \ud65c\uc6a9 \ud65c\uc6a9 \ud65c\uc6a9 \ud65c\uc6a9 \ud65c\uc6a9 \ud65c\uc6a9 \ud65c\uc6a9 \ud65c\uc6a9 \ud65c\uc6a9 \ud65c\uc6a9 \ud65c\uc6a9 \ud65c\uc6a9 \ud65c\uc6a9 \ud65c\uc6a9 \ud65c\uc6a9 \ud65c\uc6a9 \ud65c\uc6a9 \ud65c\uc6a9 \ud65c\uc6a9 \ud65c\uc6a9 \ud65c\uc6a9 \ud65c\uc6a9 \ud65c\uc6a9 \ud65c\uc6a9 \ud65c\uc6a9 \ud65c\uc6a9 \ud65c\uc6a9 \ud65c\uc6a9 \ud65c\uc6a9 \ud65c\uc6a9 \ud65c\uc6a9 \ud65c\uc6a9 \ud65c\uc6a9 \ud65c\uc6a9 \ud65c\uc6a9 \ud65c\uc6a9 \ud65c\uc6a9 \ud65c\uc6a9 \ud65c\uc6a9 \ud65c\uc6a9 \ud65c\uc6a9 \ud65c\uc6a9 \ud65c\uc6a9 \ud65c\uc6a9 \ud65c\uc6a9 \ud65c\uc6a9 \ud65c\uc6a9 \ud65c\uc6a9 \ud65c\uc6a9 \ud65c\uc6a9 \ud65c\uc6a9 \ud65c\uc6a9 \ud65c\uc6a9 \ud65c\uc6a9 \ud65c\uc6a9 \ud65c\uc6a9 \ud65c\uc6a9 \ud65c\uc6a9 \ud65c\uc6a9 \ud65c\uc6a9 \ud65c\uc6a9 \ud65c\uc6a9 \ud65c\uc6a9 \ud65c\uc6a9 \ud65c\uc6a9 \ud65c\uc6a9 \ud65c\uc6a9 \ud65c\uc6a9 \ud65c\uc6a9 \ud65c\uc6a9 \ud65c\uc6a9 \ud65c\uc6a9 \ud65c\uc6a9 \ud65c\uc6a9 \ud65c\uc6a9 \ud65c\uc6a9 \ud65c\uc6a9 \ud65c\uc6a9 \ud65c\uc6a9 \ud65c\uc6a9 \ud65c\uc6a9 \ud65c\uc6a9 \ud65c\uc6a9 \ud65c\uc6a9 \ud65c\uc6a9 \ud65c\uc6a9 \ud65c\uc6a9 \ud65c\uc6a9 \ud65c\uc6a9 \ud65c\uc6a9 \ud65c\uc6a9 \ud65c\uc6a9 \ud65c\uc6a9 \ud65c\uc6a9 \ud65c\uc6a9 \ud65c\uc6a9 \ud65c\uc6a9 \ud65c\uc6a9 \ud65c\uc6a9 \ud65c\uc6a9 \ud65c\uc6a9 \ud65c\uc6a9 \ud65c\uc6a9 \ud65c\uc6a9 \ud65c\uc6a9 \ud65c\uc6a9 \ud65c\uc6a9 \ud65c\uc6a9 \ud65c\uc6a9 \ud65c\uc6a9 \ud65c\uc6a9 \ud65c\uc6a9 \ud65c\uc6a9 \ud65c\uc6a9 \ud65c\uc6a9 \ud65c\uc6a9 \ud65c\uc6a9 \ud65c\uc6a9 \ud65c\uc6a9 \ud65c\uc6a9 \ud65c\uc6a9 \ud65c\uc6a9 \ud65c\uc6a9 \ud65c\uc6a9 \ud65c\uc6a9 \ud65c\uc6a9 \ud65c\uc6a9 \ud65c\uc6a9 \ud65c\uc6a9 \ud65c\uc6a9 \ud65c\uc6a9 \ud65c\uc6a9 \ud65c\uc6a9 \ud65c\uc6a9 \ud65c\uc6a9 \ud65c\uc6a9 \ud65c\uc6a9 \ud65c\uc6a9 \ud65c\uc6a9 \ud65c\uc6a9 \ud65c\uc6a9 \ud65c\uc6a9 \ud65c\uc6a9 \ud65c\uc6a9 \ud65c\uc6a9 \ud65c\uc6a9 \ud65c\uc6a9 \ud65c\uc6a9 \ud65c\uc6a9 \ud65c\uc6a9 \ud65c\uc6a9 \ud65c\uc6a9 \ud65c\uc6a9 \ud65c\uc6a9 \ud65c\uc6a9 \ud65c\uc6a9 \ud65c\uc6a9 \ud65c\uc6a9 \ud65c\uc6a9 \ud65c\uc6a9 \ud65c\uc6a9 \ud65c\uc6a9 \ud65c\uc6a9 \ud65c\uc6a9 \ud65c\uc6a9 \ud65c\uc6a9 \ud65c\uc6a9 \ud65c\uc6a9 \ud65c\uc6a9 \ud65c\uc6a9 \ud65c\uc6a9 \ud65c\uc6a9 \ud65c\uc6a9 \ud65c\uc6a9 \ud65c\uc6a9 \ud65c\uc6a9 \ud65c\uc6a9 \ud65c\uc6a9 \ud65c\uc6a9 \ud65c\uc6a9 \ud65c\uc6a9 \ud65c\uc6a9 \ud65c\uc6a9 \ud65c\uc6a9 \ud65c\uc6a9 \ud65c\uc6a9 \ud65c\uc6a9 \ud65c\uc6a9 \ud65c\uc6a9 \ud65c\uc6a9 \ud65c\uc6a9 \ud65c\uc6a9 \ud65c\uc6a9 \ud65c\uc6a9 \ud65c\uc6a9 \ud65c\uc6a9 \ud65c\uc6a9 \ud65c\uc6a9 \ud65c\uc6a9 \ud65c\uc6a9 \ud65c\uc6a9 \ud65c\uc6a9 \ud65c\uc6a9 \ud65c\uc6a9 \ud65c\uc6a9 \ud65c\uc6a9 \ud65c\uc6a9 \ud65c\uc6a9 \ud65c\uc6a9 \ud65c\uc6a9 \ud65c\uc6a9 \ud65c\uc6a9 \ud65c\uc6a9 \ud65c\uc6a9 \ud65c\uc6a9 \ud65c\uc6a9 \ud65c\uc6a9 \ud65c\uc6a9 \ud65c\uc6a9 \ud65c\uc6a9 \ud65c\uc6a9 \ud65c\uc6a9 \ud65c\uc6a9 \ud65c\uc6a9 \ud65c\uc6a9 \ud65c\uc6a9 \ud65c\uc6a9 \ud65c\uc6a9 \ud65c\uc6a9 \ud65c\uc6a9 \ud65c\uc6a9 \ud65c\uc6a9 \ud65c\uc6a9 \ud65c\uc6a9 \ud65c\uc6a9 \ud65c\uc6a9"
    },
    {
        "question": "How many memberships exist in the graph?",
        "query": "SELECT (count(?membership) as ?count) WHERE { ?membership a org:Membership . }",
        "generated": "\ud65c\uc6a9 \ud65c\uc6a9 \ud65c\uc6a9 \ud65c\uc6a9 \ud65c\uc6a9 \ud65c\uc6a9 \ud65c\uc6a9 \ud65c\uc6a9 \ud65c\uc6a9 \ud65c\uc6a9 \ud65c\uc6a9 \ud65c\uc6a9 \ud65c\uc6a9 \ud65c\uc6a9 \ud65c\uc6a9 \ud65c\uc6a9 \ud65c\uc6a9 \ud65c\uc6a9 \ud65c\uc6a9 \ud65c\uc6a9 \ud65c\uc6a9 \ud65c\uc6a9 \ud65c\uc6a9 \ud65c\uc6a9 \ud65c\uc6a9 \ud65c\uc6a9 \ud65c\uc6a9 \ud65c\uc6a9 \ud65c\uc6a9 \ud65c\uc6a9 \ud65c\uc6a9 \ud65c\uc6a9 \ud65c\uc6a9 \ud65c\uc6a9 \ud65c\uc6a9 \ud65c\uc6a9 \ud65c\uc6a9 \ud65c\uc6a9 \ud65c\uc6a9 \ud65c\uc6a9 \ud65c\uc6a9 \ud65c\uc6a9 \ud65c\uc6a9 \ud65c\uc6a9 \ud65c\uc6a9 \ud65c\uc6a9 \ud65c\uc6a9 \ud65c\uc6a9 \ud65c\uc6a9 \ud65c\uc6a9 \ud65c\uc6a9 \ud65c\uc6a9 \ud65c\uc6a9 \ud65c\uc6a9 \ud65c\uc6a9 \ud65c\uc6a9 \ud65c\uc6a9 \ud65c\uc6a9 \ud65c\uc6a9 \ud65c\uc6a9 \ud65c\uc6a9 \ud65c\uc6a9 \ud65c\uc6a9 \ud65c\uc6a9 \ud65c\uc6a9 \ud65c\uc6a9 \ud65c\uc6a9 \ud65c\uc6a9 \ud65c\uc6a9 \ud65c\uc6a9 \ud65c\uc6a9 \ud65c\uc6a9 \ud65c\uc6a9 \ud65c\uc6a9 \ud65c\uc6a9 \ud65c\uc6a9 \ud65c\uc6a9 \ud65c\uc6a9 \ud65c\uc6a9 \ud65c\uc6a9 \ud65c\uc6a9 \ud65c\uc6a9 \ud65c\uc6a9 \ud65c\uc6a9 \ud65c\uc6a9 \ud65c\uc6a9 \ud65c\uc6a9 \ud65c\uc6a9 \ud65c\uc6a9 \ud65c\uc6a9 \ud65c\uc6a9 \ud65c\uc6a9 \ud65c\uc6a9 \ud65c\uc6a9 \ud65c\uc6a9 \ud65c\uc6a9 \ud65c\uc6a9 \ud65c\uc6a9 \ud65c\uc6a9 \ud65c\uc6a9 \ud65c\uc6a9 \ud65c\uc6a9 \ud65c\uc6a9 \ud65c\uc6a9 \ud65c\uc6a9 \ud65c\uc6a9 \ud65c\uc6a9 \ud65c\uc6a9 \ud65c\uc6a9 \ud65c\uc6a9 \ud65c\uc6a9 \ud65c\uc6a9 \ud65c\uc6a9 \ud65c\uc6a9 \ud65c\uc6a9 \ud65c\uc6a9 \ud65c\uc6a9 \ud65c\uc6a9 \ud65c\uc6a9 \ud65c\uc6a9 \ud65c\uc6a9 \ud65c\uc6a9 \ud65c\uc6a9 \ud65c\uc6a9 \ud65c\uc6a9 \ud65c\uc6a9 \ud65c\uc6a9 \ud65c\uc6a9 \ud65c\uc6a9 \ud65c\uc6a9 \ud65c\uc6a9 \ud65c\uc6a9 \ud65c\uc6a9 \ud65c\uc6a9 \ud65c\uc6a9 \ud65c\uc6a9 \ud65c\uc6a9 \ud65c\uc6a9 \ud65c\uc6a9 \ud65c\uc6a9 \ud65c\uc6a9 \ud65c\uc6a9 \ud65c\uc6a9 \ud65c\uc6a9 \ud65c\uc6a9 \ud65c\uc6a9 \ud65c\uc6a9 \ud65c\uc6a9 \ud65c\uc6a9 \ud65c\uc6a9 \ud65c\uc6a9 \ud65c\uc6a9 \ud65c\uc6a9 \ud65c\uc6a9 \ud65c\uc6a9 \ud65c\uc6a9 \ud65c\uc6a9 \ud65c\uc6a9 \ud65c\uc6a9 \ud65c\uc6a9 \ud65c\uc6a9 \ud65c\uc6a9 \ud65c\uc6a9 \ud65c\uc6a9 \ud65c\uc6a9 \ud65c\uc6a9 \ud65c\uc6a9 \ud65c\uc6a9 \ud65c\uc6a9 \ud65c\uc6a9 \ud65c\uc6a9 \ud65c\uc6a9 \ud65c\uc6a9 \ud65c\uc6a9 \ud65c\uc6a9 \ud65c\uc6a9 \ud65c\uc6a9 \ud65c\uc6a9 \ud65c\uc6a9 \ud65c\uc6a9 \ud65c\uc6a9 \ud65c\uc6a9 \ud65c\uc6a9 \ud65c\uc6a9 \ud65c\uc6a9 \ud65c\uc6a9 \ud65c\uc6a9 \ud65c\uc6a9 \ud65c\uc6a9 \ud65c\uc6a9 \ud65c\uc6a9 \ud65c\uc6a9 \ud65c\uc6a9 \ud65c\uc6a9 \ud65c\uc6a9 \ud65c\uc6a9 \ud65c\uc6a9 \ud65c\uc6a9 \ud65c\uc6a9 \ud65c\uc6a9 \ud65c\uc6a9 \ud65c\uc6a9 \ud65c\uc6a9 \ud65c\uc6a9 \ud65c\uc6a9 \ud65c\uc6a9 \ud65c\uc6a9 \ud65c\uc6a9 \ud65c\uc6a9 \ud65c\uc6a9 \ud65c\uc6a9 \ud65c\uc6a9 \ud65c\uc6a9 \ud65c\uc6a9 \ud65c\uc6a9 \ud65c\uc6a9 \ud65c\uc6a9 \ud65c\uc6a9 \ud65c\uc6a9 \ud65c\uc6a9 \ud65c\uc6a9 \ud65c\uc6a9 \ud65c\uc6a9 \ud65c\uc6a9 \ud65c\uc6a9 \ud65c\uc6a9 \ud65c\uc6a9 \ud65c\uc6a9 \ud65c\uc6a9 \ud65c\uc6a9 \ud65c\uc6a9 \ud65c\uc6a9 \ud65c\uc6a9 \ud65c\uc6a9 \ud65c\uc6a9 \ud65c\uc6a9 \ud65c\uc6a9 \ud65c\uc6a9 \ud65c\uc6a9 \ud65c\uc6a9 \ud65c\uc6a9 \ud65c\uc6a9 \ud65c\uc6a9 \ud65c\uc6a9 \ud65c\uc6a9 \ud65c\uc6a9 \ud65c\uc6a9 \ud65c\uc6a9 \ud65c\uc6a9 \ud65c\uc6a9 \ud65c\uc6a9 \ud65c\uc6a9 \ud65c\uc6a9 \ud65c\uc6a9 \ud65c\uc6a9"
    },
    {
        "question": "How many persons are members of the research department?",
        "query": "SELECT (count(?member) as ?count) WHERE { ?member org:organization :researchDep . }",
        "generated": "\uc81c\uacf5 \uc81c\uacf5 \uc81c\uacf5 \uc81c\uacf5 \uc81c\uacf5 \uc81c\uacf5 \uc81c\uacf5 \uc81c\uacf5 \uc81c\uacf5 \uc81c\uacf5 \uc81c\uacf5 \uc81c\uacf5 \uc81c\uacf5 \uc81c\uacf5 \uc81c\uacf5 \uc81c\uacf5 \uc81c\uacf5 \uc81c\uacf5 \uc81c\uacf5 \uc81c\uacf5 \uc81c\uacf5 \uc81c\uacf5 \uc81c\uacf5 \uc81c\uacf5 \uc81c\uacf5 \uc81c\uacf5 \uc81c\uacf5 \uc81c\uacf5 \uc81c\uacf5 \uc81c\uacf5 \uc81c\uacf5 \uc81c\uacf5 \uc81c\uacf5 \uc81c\uacf5 \uc81c\uacf5 \uc81c\uacf5 \uc81c\uacf5 \uc81c\uacf5 \uc81c\uacf5 \uc81c\uacf5 \uc81c\uacf5 \uc81c\uacf5 \uc81c\uacf5 \uc81c\uacf5 \uc81c\uacf5 \uc81c\uacf5 \uc81c\uacf5 \uc81c\uacf5 \uc81c\uacf5 \uc81c\uacf5 \uc81c\uacf5 \uc81c\uacf5 \uc81c\uacf5 \uc81c\uacf5 \uc81c\uacf5 \uc81c\uacf5 \uc81c\uacf5 \uc81c\uacf5 \uc81c\uacf5 \uc81c\uacf5 \uc81c\uacf5 \uc81c\uacf5 \uc81c\uacf5 \uc81c\uacf5 \uc81c\uacf5 \uc81c\uacf5 \uc81c\uacf5 \uc81c\uacf5 \uc81c\uacf5 \uc81c\uacf5 \uc81c\uacf5 \uc81c\uacf5 \uc81c\uacf5 \uc81c\uacf5 \uc81c\uacf5 \uc81c\uacf5 \uc81c\uacf5 \uc81c\uacf5 \uc81c\uacf5 \uc81c\uacf5 \uc81c\uacf5 \uc81c\uacf5 \uc81c\uacf5 \uc81c\uacf5 \uc81c\uacf5 \uc81c\uacf5 \uc81c\uacf5 \uc81c\uacf5 \uc81c\uacf5 \uc81c\uacf5 \uc81c\uacf5 \uc81c\uacf5 \uc81c\uacf5 \uc81c\uacf5 \uc81c\uacf5 \uc81c\uacf5 \uc81c\uacf5 \uc81c\uacf5 \uc81c\uacf5 \uc81c\uacf5 \uc81c\uacf5 \uc81c\uacf5 \uc81c\uacf5 \uc81c\uacf5 \uc81c\uacf5 \uc81c\uacf5 \uc81c\uacf5 \uc81c\uacf5 \uc81c\uacf5 \uc81c\uacf5 \uc81c\uacf5 \uc81c\uacf5 \uc81c\uacf5 \uc81c\uacf5 \uc81c\uacf5 \uc81c\uacf5 \uc81c\uacf5 \uc81c\uacf5 \uc81c\uacf5 \uc81c\uacf5 \uc81c\uacf5 \uc81c\uacf5 \uc81c\uacf5 \uc81c\uacf5 \uc81c\uacf5 \uc81c\uacf5 \uc81c\uacf5 \uc81c\uacf5 \uc81c\uacf5 \uc81c\uacf5 \uc81c\uacf5 \uc81c\uacf5 \uc81c\uacf5 \uc81c\uacf5 \uc81c\uacf5 \uc81c\uacf5 \uc81c\uacf5 \uc81c\uacf5 \uc81c\uacf5 \uc81c\uacf5 \uc81c\uacf5 \uc81c\uacf5 \uc81c\uacf5 \uc81c\uacf5 \uc81c\uacf5 \uc81c\uacf5 \uc81c\uacf5 \uc81c\uacf5 \uc81c\uacf5 \uc81c\uacf5 \uc81c\uacf5 \uc81c\uacf5 \uc81c\uacf5 \uc81c\uacf5 \uc81c\uacf5 \uc81c\uacf5 \uc81c\uacf5 \uc81c\uacf5 \uc81c\uacf5 \uc81c\uacf5 \uc81c\uacf5 \uc81c\uacf5 \uc81c\uacf5 \uc81c\uacf5 \uc81c\uacf5 \uc81c\uacf5 \uc81c\uacf5 \uc81c\uacf5 \uc81c\uacf5 \uc81c\uacf5 \uc81c\uacf5 \uc81c\uacf5 \uc81c\uacf5 \uc81c\uacf5 \uc81c\uacf5 \uc81c\uacf5 \uc81c\uacf5 \uc81c\uacf5 \uc81c\uacf5 \uc81c\uacf5 \uc81c\uacf5 \uc81c\uacf5 \uc81c\uacf5 \uc81c\uacf5 \uc81c\uacf5 \uc81c\uacf5 \uc81c\uacf5 \uc81c\uacf5 \uc81c\uacf5 \uc81c\uacf5 \uc81c\uacf5 \uc81c\uacf5 \uc81c\uacf5 \uc81c\uacf5 \uc81c\uacf5 \uc81c\uacf5 \uc81c\uacf5 \uc81c\uacf5 \uc81c\uacf5 \uc81c\uacf5 \uc81c\uacf5 \uc81c\uacf5 \uc81c\uacf5 \uc81c\uacf5 \uc81c\uacf5 \uc81c\uacf5 \uc81c\uacf5 \uc81c\uacf5 \uc81c\uacf5 \uc81c\uacf5 \uc81c\uacf5 \uc81c\uacf5 \uc81c\uacf5 \uc81c\uacf5 \uc81c\uacf5 \uc81c\uacf5 \uc81c\uacf5 \uc81c\uacf5 \uc81c\uacf5 \uc81c\uacf5 \uc81c\uacf5 \uc81c\uacf5 \uc81c\uacf5 \uc81c\uacf5 \uc81c\uacf5 \uc81c\uacf5 \uc81c\uacf5 \uc81c\uacf5 \uc81c\uacf5 \uc81c\uacf5 \uc81c\uacf5 \uc81c\uacf5 \uc81c\uacf5 \uc81c\uacf5 \uc81c\uacf5 \uc81c\uacf5 \uc81c\uacf5 \uc81c\uacf5 \uc81c\uacf5 \uc81c\uacf5 \uc81c\uacf5 \uc81c\uacf5 \uc81c\uacf5 \uc81c\uacf5 \uc81c\uacf5 \uc81c\uacf5 \uc81c\uacf5 \uc81c\uacf5 \uc81c\uacf5 \uc81c\uacf5 \uc81c\uacf5 \uc81c\uacf5 \uc81c\uacf5 \uc81c\uacf5 \uc81c\uacf5"
    },
    {
        "question": "How many persons are members of the marketing department?",
        "query": "SELECT (count(?member) as ?count) WHERE { ?member org:organization :marketingDep . }",
        "generated": "\uc81c\uacf5 \uc81c\uacf5 \uc81c\uacf5 \uc81c\uacf5 \uc81c\uacf5 \uc81c\uacf5 \uc81c\uacf5 \uc81c\uacf5 \uc81c\uacf5 \uc81c\uacf5 \uc81c\uacf5 \uc81c\uacf5 \uc81c\uacf5 \uc81c\uacf5 \uc81c\uacf5 \uc81c\uacf5 \uc81c\uacf5 \uc81c\uacf5 \uc81c\uacf5 \uc81c\uacf5 \uc81c\uacf5 \uc81c\uacf5 \uc81c\uacf5 \uc81c\uacf5 \uc81c\uacf5 \uc81c\uacf5 \uc81c\uacf5 \uc81c\uacf5 \uc81c\uacf5 \uc81c\uacf5 \uc81c\uacf5 \uc81c\uacf5 \uc81c\uacf5 \uc81c\uacf5 \uc81c\uacf5 \uc81c\uacf5 \uc81c\uacf5 \uc81c\uacf5 \uc81c\uacf5 \uc81c\uacf5 \uc81c\uacf5 \uc81c\uacf5 \uc81c\uacf5 \uc81c\uacf5 \uc81c\uacf5 \uc81c\uacf5 \uc81c\uacf5 \uc81c\uacf5 \uc81c\uacf5 \uc81c\uacf5 \uc81c\uacf5 \uc81c\uacf5 \uc81c\uacf5 \uc81c\uacf5 \uc81c\uacf5 \uc81c\uacf5 \uc81c\uacf5 \uc81c\uacf5 \uc81c\uacf5 \uc81c\uacf5 \uc81c\uacf5 \uc81c\uacf5 \uc81c\uacf5 \uc81c\uacf5 \uc81c\uacf5 \uc81c\uacf5 \uc81c\uacf5 \uc81c\uacf5 \uc81c\uacf5 \uc81c\uacf5 \uc81c\uacf5 \uc81c\uacf5 \uc81c\uacf5 \uc81c\uacf5 \uc81c\uacf5 \uc81c\uacf5 \uc81c\uacf5 \uc81c\uacf5 \uc81c\uacf5 \uc81c\uacf5 \uc81c\uacf5 \uc81c\uacf5 \uc81c\uacf5 \uc81c\uacf5 \uc81c\uacf5 \uc81c\uacf5 \uc81c\uacf5 \uc81c\uacf5 \uc81c\uacf5 \uc81c\uacf5 \uc81c\uacf5 \uc81c\uacf5 \uc81c\uacf5 \uc81c\uacf5 \uc81c\uacf5 \uc81c\uacf5 \uc81c\uacf5 \uc81c\uacf5 \uc81c\uacf5 \uc81c\uacf5 \uc81c\uacf5 \uc81c\uacf5 \uc81c\uacf5 \uc81c\uacf5 \uc81c\uacf5 \uc81c\uacf5 \uc81c\uacf5 \uc81c\uacf5 \uc81c\uacf5 \uc81c\uacf5 \uc81c\uacf5 \uc81c\uacf5 \uc81c\uacf5 \uc81c\uacf5 \uc81c\uacf5 \uc81c\uacf5 \uc81c\uacf5 \uc81c\uacf5 \uc81c\uacf5 \uc81c\uacf5 \uc81c\uacf5 \uc81c\uacf5 \uc81c\uacf5 \uc81c\uacf5 \uc81c\uacf5 \uc81c\uacf5 \uc81c\uacf5 \uc81c\uacf5 \uc81c\uacf5 \uc81c\uacf5 \uc81c\uacf5 \uc81c\uacf5 \uc81c\uacf5 \uc81c\uacf5 \uc81c\uacf5 \uc81c\uacf5 \uc81c\uacf5 \uc81c\uacf5 \uc81c\uacf5 \uc81c\uacf5 \uc81c\uacf5 \uc81c\uacf5 \uc81c\uacf5 \uc81c\uacf5 \uc81c\uacf5 \uc81c\uacf5 \uc81c\uacf5 \uc81c\uacf5 \uc81c\uacf5 \uc81c\uacf5 \uc81c\uacf5 \uc81c\uacf5 \uc81c\uacf5 \uc81c\uacf5 \uc81c\uacf5 \uc81c\uacf5 \uc81c\uacf5 \uc81c\uacf5 \uc81c\uacf5 \uc81c\uacf5 \uc81c\uacf5 \uc81c\uacf5 \uc81c\uacf5 \uc81c\uacf5 \uc81c\uacf5 \uc81c\uacf5 \uc81c\uacf5 \uc81c\uacf5 \uc81c\uacf5 \uc81c\uacf5 \uc81c\uacf5 \uc81c\uacf5 \uc81c\uacf5 \uc81c\uacf5 \uc81c\uacf5 \uc81c\uacf5 \uc81c\uacf5 \uc81c\uacf5 \uc81c\uacf5 \uc81c\uacf5 \uc81c\uacf5 \uc81c\uacf5 \uc81c\uacf5 \uc81c\uacf5 \uc81c\uacf5 \uc81c\uacf5 \uc81c\uacf5 \uc81c\uacf5 \uc81c\uacf5 \uc81c\uacf5 \uc81c\uacf5 \uc81c\uacf5 \uc81c\uacf5 \uc81c\uacf5 \uc81c\uacf5 \uc81c\uacf5 \uc81c\uacf5 \uc81c\uacf5 \uc81c\uacf5 \uc81c\uacf5 \uc81c\uacf5 \uc81c\uacf5 \uc81c\uacf5 \uc81c\uacf5 \uc81c\uacf5 \uc81c\uacf5 \uc81c\uacf5 \uc81c\uacf5 \uc81c\uacf5 \uc81c\uacf5 \uc81c\uacf5 \uc81c\uacf5 \uc81c\uacf5 \uc81c\uacf5 \uc81c\uacf5 \uc81c\uacf5 \uc81c\uacf5 \uc81c\uacf5 \uc81c\uacf5 \uc81c\uacf5 \uc81c\uacf5 \uc81c\uacf5 \uc81c\uacf5 \uc81c\uacf5 \uc81c\uacf5 \uc81c\uacf5 \uc81c\uacf5 \uc81c\uacf5 \uc81c\uacf5 \uc81c\uacf5 \uc81c\uacf5 \uc81c\uacf5 \uc81c\uacf5 \uc81c\uacf5 \uc81c\uacf5 \uc81c\uacf5 \uc81c\uacf5 \uc81c\uacf5 \uc81c\uacf5 \uc81c\uacf5 \uc81c\uacf5 \uc81c\uacf5 \uc81c\uacf5 \uc81c\uacf5 \uc81c\uacf5 \uc81c\uacf5 \uc81c\uacf5 \uc81c\uacf5 \uc81c\uacf5 \uc81c\uacf5 \uc81c\uacf5 \uc81c\uacf5 \uc81c\uacf5 \uc81c\uacf5 \uc81c\uacf5"
    },
    {
        "question": "How many persons have a home address?",
        "query": "SELECT (count(?person) as ?count) WHERE { ?person vcard:hasAddress [] . }",
        "generated": "\ud65c\uc6a9 \ud65c\uc6a9 \ud65c\uc6a9 \ud65c\uc6a9 \ud65c\uc6a9 \ud65c\uc6a9 \ud65c\uc6a9 \ud65c\uc6a9 \ud65c\uc6a9 \ud65c\uc6a9 \ud65c\uc6a9 \ud65c\uc6a9 \ud65c\uc6a9 \ud65c\uc6a9 \ud65c\uc6a9 \ud65c\uc6a9 \ud65c\uc6a9 \ud65c\uc6a9 \ud65c\uc6a9 \ud65c\uc6a9 \ud65c\uc6a9 \ud65c\uc6a9 \ud65c\uc6a9 \ud65c\uc6a9 \ud65c\uc6a9 \ud65c\uc6a9 \ud65c\uc6a9 \ud65c\uc6a9 \ud65c\uc6a9 \ud65c\uc6a9 \ud65c\uc6a9 \ud65c\uc6a9 \ud65c\uc6a9 \ud65c\uc6a9 \ud65c\uc6a9 \ud65c\uc6a9 \ud65c\uc6a9 \ud65c\uc6a9 \ud65c\uc6a9 \ud65c\uc6a9 \ud65c\uc6a9 \ud65c\uc6a9 \ud65c\uc6a9 \ud65c\uc6a9 \ud65c\uc6a9 \ud65c\uc6a9 \ud65c\uc6a9 \ud65c\uc6a9 \ud65c\uc6a9 \ud65c\uc6a9 \ud65c\uc6a9 \ud65c\uc6a9 \ud65c\uc6a9 \ud65c\uc6a9 \ud65c\uc6a9 \ud65c\uc6a9 \ud65c\uc6a9 \ud65c\uc6a9 \ud65c\uc6a9 \ud65c\uc6a9 \ud65c\uc6a9 \ud65c\uc6a9 \ud65c\uc6a9 \ud65c\uc6a9 \ud65c\uc6a9 \ud65c\uc6a9 \ud65c\uc6a9 \ud65c\uc6a9 \ud65c\uc6a9 \ud65c\uc6a9 \ud65c\uc6a9 \ud65c\uc6a9 \ud65c\uc6a9 \ud65c\uc6a9 \ud65c\uc6a9 \ud65c\uc6a9 \ud65c\uc6a9 \ud65c\uc6a9 \ud65c\uc6a9 \ud65c\uc6a9 \ud65c\uc6a9 \ud65c\uc6a9 \ud65c\uc6a9 \ud65c\uc6a9 \ud65c\uc6a9 \ud65c\uc6a9 \ud65c\uc6a9 \ud65c\uc6a9 \ud65c\uc6a9 \ud65c\uc6a9 \ud65c\uc6a9 \ud65c\uc6a9 \ud65c\uc6a9 \ud65c\uc6a9 \ud65c\uc6a9 \ud65c\uc6a9 \ud65c\uc6a9 \ud65c\uc6a9 \ud65c\uc6a9 \ud65c\uc6a9 \ud65c\uc6a9 \ud65c\uc6a9 \ud65c\uc6a9 \ud65c\uc6a9 \ud65c\uc6a9 \ud65c\uc6a9 \ud65c\uc6a9 \ud65c\uc6a9 \ud65c\uc6a9 \ud65c\uc6a9 \ud65c\uc6a9 \ud65c\uc6a9 \ud65c\uc6a9 \ud65c\uc6a9 \ud65c\uc6a9 \ud65c\uc6a9 \ud65c\uc6a9 \ud65c\uc6a9 \ud65c\uc6a9 \ud65c\uc6a9 \ud65c\uc6a9 \ud65c\uc6a9 \ud65c\uc6a9 \ud65c\uc6a9 \ud65c\uc6a9 \ud65c\uc6a9 \ud65c\uc6a9 \ud65c\uc6a9 \ud65c\uc6a9 \ud65c\uc6a9 \ud65c\uc6a9 \ud65c\uc6a9 \ud65c\uc6a9 \ud65c\uc6a9 \ud65c\uc6a9 \ud65c\uc6a9 \ud65c\uc6a9 \ud65c\uc6a9 \ud65c\uc6a9 \ud65c\uc6a9 \ud65c\uc6a9 \ud65c\uc6a9 \ud65c\uc6a9 \ud65c\uc6a9 \ud65c\uc6a9 \ud65c\uc6a9 \ud65c\uc6a9 \ud65c\uc6a9 \ud65c\uc6a9 \ud65c\uc6a9 \ud65c\uc6a9 \ud65c\uc6a9 \ud65c\uc6a9 \ud65c\uc6a9 \ud65c\uc6a9 \ud65c\uc6a9 \ud65c\uc6a9 \ud65c\uc6a9 \ud65c\uc6a9 \ud65c\uc6a9 \ud65c\uc6a9 \ud65c\uc6a9 \ud65c\uc6a9 \ud65c\uc6a9 \ud65c\uc6a9 \ud65c\uc6a9 \ud65c\uc6a9 \ud65c\uc6a9 \ud65c\uc6a9 \ud65c\uc6a9 \ud65c\uc6a9 \ud65c\uc6a9 \ud65c\uc6a9 \ud65c\uc6a9 \ud65c\uc6a9 \ud65c\uc6a9 \ud65c\uc6a9 \ud65c\uc6a9 \ud65c\uc6a9 \ud65c\uc6a9 \ud65c\uc6a9 \ud65c\uc6a9 \ud65c\uc6a9 \ud65c\uc6a9 \ud65c\uc6a9 \ud65c\uc6a9 \ud65c\uc6a9 \ud65c\uc6a9 \ud65c\uc6a9 \ud65c\uc6a9 \ud65c\uc6a9 \ud65c\uc6a9 \ud65c\uc6a9 \ud65c\uc6a9 \ud65c\uc6a9 \ud65c\uc6a9 \ud65c\uc6a9 \ud65c\uc6a9 \ud65c\uc6a9 \ud65c\uc6a9 \ud65c\uc6a9 \ud65c\uc6a9 \ud65c\uc6a9 \ud65c\uc6a9 \ud65c\uc6a9 \ud65c\uc6a9 \ud65c\uc6a9 \ud65c\uc6a9 \ud65c\uc6a9 \ud65c\uc6a9 \ud65c\uc6a9 \ud65c\uc6a9 \ud65c\uc6a9 \ud65c\uc6a9 \ud65c\uc6a9 \ud65c\uc6a9 \ud65c\uc6a9 \ud65c\uc6a9 \ud65c\uc6a9 \ud65c\uc6a9 \ud65c\uc6a9 \ud65c\uc6a9 \ud65c\uc6a9 \ud65c\uc6a9 \ud65c\uc6a9 \ud65c\uc6a9 \ud65c\uc6a9 \ud65c\uc6a9 \ud65c\uc6a9 \ud65c\uc6a9 \ud65c\uc6a9 \ud65c\uc6a9 \ud65c\uc6a9 \ud65c\uc6a9 \ud65c\uc6a9 \ud65c\uc6a9 \ud65c\uc6a9 \ud65c\uc6a9 \ud65c\uc6a9 \ud65c\uc6a9 \ud65c\uc6a9 \ud65c\uc6a9 \ud65c\uc6a9 \ud65c\uc6a9 \ud65c\uc6a9 \ud65c\uc6a9 \ud65c\uc6a9 \ud65c\uc6a9 \ud65c\uc6a9 \ud65c\uc6a9 \ud65c\uc6a9 \ud65c\uc6a9 \ud65c\uc6a9 \ud65c\uc6a9 \ud65c\uc6a9"
    },
    {
        "question": "How many persons have a home address in the UK?",
        "query": "SELECT (count(?person) as ?count) WHERE { ?person vcard:hasAddress [ vcard:country-name 'UK' ] . }",
        "generated": "\ud65c\uc6a9 \ud65c\uc6a9 \ud65c\uc6a9 \ud65c\uc6a9 \ud65c\uc6a9 \ud65c\uc6a9 \ud65c\uc6a9 \ud65c\uc6a9 \ud65c\uc6a9 \ud65c\uc6a9 \ud65c\uc6a9 \ud65c\uc6a9 \ud65c\uc6a9 \ud65c\uc6a9 \ud65c\uc6a9 \ud65c\uc6a9 \ud65c\uc6a9 \ud65c\uc6a9 \ud65c\uc6a9 \ud65c\uc6a9 \ud65c\uc6a9 \ud65c\uc6a9 \ud65c\uc6a9 \ud65c\uc6a9 \ud65c\uc6a9 \ud65c\uc6a9 \ud65c\uc6a9 \ud65c\uc6a9 \ud65c\uc6a9 \ud65c\uc6a9 \ud65c\uc6a9 \ud65c\uc6a9 \ud65c\uc6a9 \ud65c\uc6a9 \ud65c\uc6a9 \ud65c\uc6a9 \ud65c\uc6a9 \ud65c\uc6a9 \ud65c\uc6a9 \ud65c\uc6a9 \ud65c\uc6a9 \ud65c\uc6a9 \ud65c\uc6a9 \ud65c\uc6a9 \ud65c\uc6a9 \ud65c\uc6a9 \ud65c\uc6a9 \ud65c\uc6a9 \ud65c\uc6a9 \ud65c\uc6a9 \ud65c\uc6a9 \ud65c\uc6a9 \ud65c\uc6a9 \ud65c\uc6a9 \ud65c\uc6a9 \ud65c\uc6a9 \ud65c\uc6a9 \ud65c\uc6a9 \ud65c\uc6a9 \ud65c\uc6a9 \ud65c\uc6a9 \ud65c\uc6a9 \ud65c\uc6a9 \ud65c\uc6a9 \ud65c\uc6a9 \ud65c\uc6a9 \ud65c\uc6a9 \ud65c\uc6a9 \ud65c\uc6a9 \ud65c\uc6a9 \ud65c\uc6a9 \ud65c\uc6a9 \ud65c\uc6a9 \ud65c\uc6a9 \ud65c\uc6a9 \ud65c\uc6a9 \ud65c\uc6a9 \ud65c\uc6a9 \ud65c\uc6a9 \ud65c\uc6a9 \ud65c\uc6a9 \ud65c\uc6a9 \ud65c\uc6a9 \ud65c\uc6a9 \ud65c\uc6a9 \ud65c\uc6a9 \ud65c\uc6a9 \ud65c\uc6a9 \ud65c\uc6a9 \ud65c\uc6a9 \ud65c\uc6a9 \ud65c\uc6a9 \ud65c\uc6a9 \ud65c\uc6a9 \ud65c\uc6a9 \ud65c\uc6a9 \ud65c\uc6a9 \ud65c\uc6a9 \ud65c\uc6a9 \ud65c\uc6a9 \ud65c\uc6a9 \ud65c\uc6a9 \ud65c\uc6a9 \ud65c\uc6a9 \ud65c\uc6a9 \ud65c\uc6a9 \ud65c\uc6a9 \ud65c\uc6a9 \ud65c\uc6a9 \ud65c\uc6a9 \ud65c\uc6a9 \ud65c\uc6a9 \ud65c\uc6a9 \ud65c\uc6a9 \ud65c\uc6a9 \ud65c\uc6a9 \ud65c\uc6a9 \ud65c\uc6a9 \ud65c\uc6a9 \ud65c\uc6a9 \ud65c\uc6a9 \ud65c\uc6a9 \ud65c\uc6a9 \ud65c\uc6a9 \ud65c\uc6a9 \ud65c\uc6a9 \ud65c\uc6a9 \ud65c\uc6a9 \ud65c\uc6a9 \ud65c\uc6a9 \ud65c\uc6a9 \ud65c\uc6a9 \ud65c\uc6a9 \ud65c\uc6a9 \ud65c\uc6a9 \ud65c\uc6a9 \ud65c\uc6a9 \ud65c\uc6a9 \ud65c\uc6a9 \ud65c\uc6a9 \ud65c\uc6a9 \ud65c\uc6a9 \ud65c\uc6a9 \ud65c\uc6a9 \ud65c\uc6a9 \ud65c\uc6a9 \ud65c\uc6a9 \ud65c\uc6a9 \ud65c\uc6a9 \ud65c\uc6a9 \ud65c\uc6a9 \ud65c\uc6a9 \ud65c\uc6a9 \ud65c\uc6a9 \ud65c\uc6a9 \ud65c\uc6a9 \ud65c\uc6a9 \ud65c\uc6a9 \ud65c\uc6a9 \ud65c\uc6a9 \ud65c\uc6a9 \ud65c\uc6a9 \ud65c\uc6a9 \ud65c\uc6a9 \ud65c\uc6a9 \ud65c\uc6a9 \ud65c\uc6a9 \ud65c\uc6a9 \ud65c\uc6a9 \ud65c\uc6a9 \ud65c\uc6a9 \ud65c\uc6a9 \ud65c\uc6a9 \ud65c\uc6a9 \ud65c\uc6a9 \ud65c\uc6a9 \ud65c\uc6a9 \ud65c\uc6a9 \ud65c\uc6a9 \ud65c\uc6a9 \ud65c\uc6a9 \ud65c\uc6a9 \ud65c\uc6a9 \ud65c\uc6a9 \ud65c\uc6a9 \ud65c\uc6a9 \ud65c\uc6a9 \ud65c\uc6a9 \ud65c\uc6a9 \ud65c\uc6a9 \ud65c\uc6a9 \ud65c\uc6a9 \ud65c\uc6a9 \ud65c\uc6a9 \ud65c\uc6a9 \ud65c\uc6a9 \ud65c\uc6a9 \ud65c\uc6a9 \ud65c\uc6a9 \ud65c\uc6a9 \ud65c\uc6a9 \ud65c\uc6a9 \ud65c\uc6a9 \ud65c\uc6a9 \ud65c\uc6a9 \ud65c\uc6a9 \ud65c\uc6a9 \ud65c\uc6a9 \ud65c\uc6a9 \ud65c\uc6a9 \ud65c\uc6a9 \ud65c\uc6a9 \ud65c\uc6a9 \ud65c\uc6a9 \ud65c\uc6a9 \ud65c\uc6a9 \ud65c\uc6a9 \ud65c\uc6a9 \ud65c\uc6a9 \ud65c\uc6a9 \ud65c\uc6a9 \ud65c\uc6a9 \ud65c\uc6a9 \ud65c\uc6a9 \ud65c\uc6a9 \ud65c\uc6a9 \ud65c\uc6a9 \ud65c\uc6a9 \ud65c\uc6a9 \ud65c\uc6a9 \ud65c\uc6a9 \ud65c\uc6a9 \ud65c\uc6a9 \ud65c\uc6a9 \ud65c\uc6a9 \ud65c\uc6a9 \ud65c\uc6a9 \ud65c\uc6a9 \ud65c\uc6a9 \ud65c\uc6a9 \ud65c\uc6a9 \ud65c\uc6a9 \ud65c\uc6a9 \ud65c\uc6a9 \ud65c\uc6a9 \ud65c\uc6a9 \ud65c\uc6a9 \ud65c\uc6a9 \ud65c\uc6a9 \ud65c\uc6a9 \ud65c\uc6a9 \ud65c\uc6a9 \ud65c\uc6a9 \ud65c\uc6a9 \ud65c\uc6a9"
    },
    {
        "question": "How many persons have a home address in the US?",
        "query": "SELECT (count(?person) as ?count) WHERE { ?person vcard:hasAddress [ vcard:country-name 'US' ] . }",
        "generated": "\ud65c\uc6a9 \ud65c\uc6a9 \ud65c\uc6a9 \ud65c\uc6a9 \ud65c\uc6a9 \ud65c\uc6a9 \ud65c\uc6a9 \ud65c\uc6a9 \ud65c\uc6a9 \ud65c\uc6a9 \ud65c\uc6a9 \ud65c\uc6a9 \ud65c\uc6a9 \ud65c\uc6a9 \ud65c\uc6a9 \ud65c\uc6a9 \ud65c\uc6a9 \ud65c\uc6a9 \ud65c\uc6a9 \ud65c\uc6a9 \ud65c\uc6a9 \ud65c\uc6a9 \ud65c\uc6a9 \ud65c\uc6a9 \ud65c\uc6a9 \ud65c\uc6a9 \ud65c\uc6a9 \ud65c\uc6a9 \ud65c\uc6a9 \ud65c\uc6a9 \ud65c\uc6a9 \ud65c\uc6a9 \ud65c\uc6a9 \ud65c\uc6a9 \ud65c\uc6a9 \ud65c\uc6a9 \ud65c\uc6a9 \ud65c\uc6a9 \ud65c\uc6a9 \ud65c\uc6a9 \ud65c\uc6a9 \ud65c\uc6a9 \ud65c\uc6a9 \ud65c\uc6a9 \ud65c\uc6a9 \ud65c\uc6a9 \ud65c\uc6a9 \ud65c\uc6a9 \ud65c\uc6a9 \ud65c\uc6a9 \ud65c\uc6a9 \ud65c\uc6a9 \ud65c\uc6a9 \ud65c\uc6a9 \ud65c\uc6a9 \ud65c\uc6a9 \ud65c\uc6a9 \ud65c\uc6a9 \ud65c\uc6a9 \ud65c\uc6a9 \ud65c\uc6a9 \ud65c\uc6a9 \ud65c\uc6a9 \ud65c\uc6a9 \ud65c\uc6a9 \ud65c\uc6a9 \ud65c\uc6a9 \ud65c\uc6a9 \ud65c\uc6a9 \ud65c\uc6a9 \ud65c\uc6a9 \ud65c\uc6a9 \ud65c\uc6a9 \ud65c\uc6a9 \ud65c\uc6a9 \ud65c\uc6a9 \ud65c\uc6a9 \ud65c\uc6a9 \ud65c\uc6a9 \ud65c\uc6a9 \ud65c\uc6a9 \ud65c\uc6a9 \ud65c\uc6a9 \ud65c\uc6a9 \ud65c\uc6a9 \ud65c\uc6a9 \ud65c\uc6a9 \ud65c\uc6a9 \ud65c\uc6a9 \ud65c\uc6a9 \ud65c\uc6a9 \ud65c\uc6a9 \ud65c\uc6a9 \ud65c\uc6a9 \ud65c\uc6a9 \ud65c\uc6a9 \ud65c\uc6a9 \ud65c\uc6a9 \ud65c\uc6a9 \ud65c\uc6a9 \ud65c\uc6a9 \ud65c\uc6a9 \ud65c\uc6a9 \ud65c\uc6a9 \ud65c\uc6a9 \ud65c\uc6a9 \ud65c\uc6a9 \ud65c\uc6a9 \ud65c\uc6a9 \ud65c\uc6a9 \ud65c\uc6a9 \ud65c\uc6a9 \ud65c\uc6a9 \ud65c\uc6a9 \ud65c\uc6a9 \ud65c\uc6a9 \ud65c\uc6a9 \ud65c\uc6a9 \ud65c\uc6a9 \ud65c\uc6a9 \ud65c\uc6a9 \ud65c\uc6a9 \ud65c\uc6a9 \ud65c\uc6a9 \ud65c\uc6a9 \ud65c\uc6a9 \ud65c\uc6a9 \ud65c\uc6a9 \ud65c\uc6a9 \ud65c\uc6a9 \ud65c\uc6a9 \ud65c\uc6a9 \ud65c\uc6a9 \ud65c\uc6a9 \ud65c\uc6a9 \ud65c\uc6a9 \ud65c\uc6a9 \ud65c\uc6a9 \ud65c\uc6a9 \ud65c\uc6a9 \ud65c\uc6a9 \ud65c\uc6a9 \ud65c\uc6a9 \ud65c\uc6a9 \ud65c\uc6a9 \ud65c\uc6a9 \ud65c\uc6a9 \ud65c\uc6a9 \ud65c\uc6a9 \ud65c\uc6a9 \ud65c\uc6a9 \ud65c\uc6a9 \ud65c\uc6a9 \ud65c\uc6a9 \ud65c\uc6a9 \ud65c\uc6a9 \ud65c\uc6a9 \ud65c\uc6a9 \ud65c\uc6a9 \ud65c\uc6a9 \ud65c\uc6a9 \ud65c\uc6a9 \ud65c\uc6a9 \ud65c\uc6a9 \ud65c\uc6a9 \ud65c\uc6a9 \ud65c\uc6a9 \ud65c\uc6a9 \ud65c\uc6a9 \ud65c\uc6a9 \ud65c\uc6a9 \ud65c\uc6a9 \ud65c\uc6a9 \ud65c\uc6a9 \ud65c\uc6a9 \ud65c\uc6a9 \ud65c\uc6a9 \ud65c\uc6a9 \ud65c\uc6a9 \ud65c\uc6a9 \ud65c\uc6a9 \ud65c\uc6a9 \ud65c\uc6a9 \ud65c\uc6a9 \ud65c\uc6a9 \ud65c\uc6a9 \ud65c\uc6a9 \ud65c\uc6a9 \ud65c\uc6a9 \ud65c\uc6a9 \ud65c\uc6a9 \ud65c\uc6a9 \ud65c\uc6a9 \ud65c\uc6a9 \ud65c\uc6a9 \ud65c\uc6a9 \ud65c\uc6a9 \ud65c\uc6a9 \ud65c\uc6a9 \ud65c\uc6a9 \ud65c\uc6a9 \ud65c\uc6a9 \ud65c\uc6a9 \ud65c\uc6a9 \ud65c\uc6a9 \ud65c\uc6a9 \ud65c\uc6a9 \ud65c\uc6a9 \ud65c\uc6a9 \ud65c\uc6a9 \ud65c\uc6a9 \ud65c\uc6a9 \ud65c\uc6a9 \ud65c\uc6a9 \ud65c\uc6a9 \ud65c\uc6a9 \ud65c\uc6a9 \ud65c\uc6a9 \ud65c\uc6a9 \ud65c\uc6a9 \ud65c\uc6a9 \ud65c\uc6a9 \ud65c\uc6a9 \ud65c\uc6a9 \ud65c\uc6a9 \ud65c\uc6a9 \ud65c\uc6a9 \ud65c\uc6a9 \ud65c\uc6a9 \ud65c\uc6a9 \ud65c\uc6a9 \ud65c\uc6a9 \ud65c\uc6a9 \ud65c\uc6a9 \ud65c\uc6a9 \ud65c\uc6a9 \ud65c\uc6a9 \ud65c\uc6a9 \ud65c\uc6a9 \ud65c\uc6a9 \ud65c\uc6a9 \ud65c\uc6a9 \ud65c\uc6a9 \ud65c\uc6a9 \ud65c\uc6a9 \ud65c\uc6a9 \ud65c\uc6a9 \ud65c\uc6a9 \ud65c\uc6a9 \ud65c\uc6a9 \ud65c\uc6a9 \ud65c\uc6a9 \ud65c\uc6a9 \ud65c\uc6a9 \ud65c\uc6a9"
    },
    {
        "question": "How many roles exist in the graph?",
        "query": "SELECT (count(?role) as ?count) WHERE { ?role a org:Role . }",
        "generated": "\ud65c\uc6a9 \ud65c\uc6a9 \ud65c\uc6a9 \ud65c\uc6a9 \ud65c\uc6a9 \ud65c\uc6a9 \ud65c\uc6a9 \ud65c\uc6a9 \ud65c\uc6a9 \ud65c\uc6a9 \ud65c\uc6a9 \ud65c\uc6a9 \ud65c\uc6a9 \ud65c\uc6a9 \ud65c\uc6a9 \ud65c\uc6a9 \ud65c\uc6a9 \ud65c\uc6a9 \ud65c\uc6a9 \ud65c\uc6a9 \ud65c\uc6a9 \ud65c\uc6a9 \ud65c\uc6a9 \ud65c\uc6a9 \ud65c\uc6a9 \ud65c\uc6a9 \ud65c\uc6a9 \ud65c\uc6a9 \ud65c\uc6a9 \ud65c\uc6a9 \ud65c\uc6a9 \ud65c\uc6a9 \ud65c\uc6a9 \ud65c\uc6a9 \ud65c\uc6a9 \ud65c\uc6a9 \ud65c\uc6a9 \ud65c\uc6a9 \ud65c\uc6a9 \ud65c\uc6a9 \ud65c\uc6a9 \ud65c\uc6a9 \ud65c\uc6a9 \ud65c\uc6a9 \ud65c\uc6a9 \ud65c\uc6a9 \ud65c\uc6a9 \ud65c\uc6a9 \ud65c\uc6a9 \ud65c\uc6a9 \ud65c\uc6a9 \ud65c\uc6a9 \ud65c\uc6a9 \ud65c\uc6a9 \ud65c\uc6a9 \ud65c\uc6a9 \ud65c\uc6a9 \ud65c\uc6a9 \ud65c\uc6a9 \ud65c\uc6a9 \ud65c\uc6a9 \ud65c\uc6a9 \ud65c\uc6a9 \ud65c\uc6a9 \ud65c\uc6a9 \ud65c\uc6a9 \ud65c\uc6a9 \ud65c\uc6a9 \ud65c\uc6a9 \ud65c\uc6a9 \ud65c\uc6a9 \ud65c\uc6a9 \ud65c\uc6a9 \ud65c\uc6a9 \ud65c\uc6a9 \ud65c\uc6a9 \ud65c\uc6a9 \ud65c\uc6a9 \ud65c\uc6a9 \ud65c\uc6a9 \ud65c\uc6a9 \ud65c\uc6a9 \ud65c\uc6a9 \ud65c\uc6a9 \ud65c\uc6a9 \ud65c\uc6a9 \ud65c\uc6a9 \ud65c\uc6a9 \ud65c\uc6a9 \ud65c\uc6a9 \ud65c\uc6a9 \ud65c\uc6a9 \ud65c\uc6a9 \ud65c\uc6a9 \ud65c\uc6a9 \ud65c\uc6a9 \ud65c\uc6a9 \ud65c\uc6a9 \ud65c\uc6a9 \ud65c\uc6a9 \ud65c\uc6a9 \ud65c\uc6a9 \ud65c\uc6a9 \ud65c\uc6a9 \ud65c\uc6a9 \ud65c\uc6a9 \ud65c\uc6a9 \ud65c\uc6a9 \ud65c\uc6a9 \ud65c\uc6a9 \ud65c\uc6a9 \ud65c\uc6a9 \ud65c\uc6a9 \ud65c\uc6a9 \ud65c\uc6a9 \ud65c\uc6a9 \ud65c\uc6a9 \ud65c\uc6a9 \ud65c\uc6a9 \ud65c\uc6a9 \ud65c\uc6a9 \ud65c\uc6a9 \ud65c\uc6a9 \ud65c\uc6a9 \ud65c\uc6a9 \ud65c\uc6a9 \ud65c\uc6a9 \ud65c\uc6a9 \ud65c\uc6a9 \ud65c\uc6a9 \ud65c\uc6a9 \ud65c\uc6a9 \ud65c\uc6a9 \ud65c\uc6a9 \ud65c\uc6a9 \ud65c\uc6a9 \ud65c\uc6a9 \ud65c\uc6a9 \ud65c\uc6a9 \ud65c\uc6a9 \ud65c\uc6a9 \ud65c\uc6a9 \ud65c\uc6a9 \ud65c\uc6a9 \ud65c\uc6a9 \ud65c\uc6a9 \ud65c\uc6a9 \ud65c\uc6a9 \ud65c\uc6a9 \ud65c\uc6a9 \ud65c\uc6a9 \ud65c\uc6a9 \ud65c\uc6a9 \ud65c\uc6a9 \ud65c\uc6a9 \ud65c\uc6a9 \ud65c\uc6a9 \ud65c\uc6a9 \ud65c\uc6a9 \ud65c\uc6a9 \ud65c\uc6a9 \ud65c\uc6a9 \ud65c\uc6a9 \ud65c\uc6a9 \ud65c\uc6a9 \ud65c\uc6a9 \ud65c\uc6a9 \ud65c\uc6a9 \ud65c\uc6a9 \ud65c\uc6a9 \ud65c\uc6a9 \ud65c\uc6a9 \ud65c\uc6a9 \ud65c\uc6a9 \ud65c\uc6a9 \ud65c\uc6a9 \ud65c\uc6a9 \ud65c\uc6a9 \ud65c\uc6a9 \ud65c\uc6a9 \ud65c\uc6a9 \ud65c\uc6a9 \ud65c\uc6a9 \ud65c\uc6a9 \ud65c\uc6a9 \ud65c\uc6a9 \ud65c\uc6a9 \ud65c\uc6a9 \ud65c\uc6a9 \ud65c\uc6a9 \ud65c\uc6a9 \ud65c\uc6a9 \ud65c\uc6a9 \ud65c\uc6a9 \ud65c\uc6a9 \ud65c\uc6a9 \ud65c\uc6a9 \ud65c\uc6a9 \ud65c\uc6a9 \ud65c\uc6a9 \ud65c\uc6a9 \ud65c\uc6a9 \ud65c\uc6a9 \ud65c\uc6a9 \ud65c\uc6a9 \ud65c\uc6a9 \ud65c\uc6a9 \ud65c\uc6a9 \ud65c\uc6a9 \ud65c\uc6a9 \ud65c\uc6a9 \ud65c\uc6a9 \ud65c\uc6a9 \ud65c\uc6a9 \ud65c\uc6a9 \ud65c\uc6a9 \ud65c\uc6a9 \ud65c\uc6a9 \ud65c\uc6a9 \ud65c\uc6a9 \ud65c\uc6a9 \ud65c\uc6a9 \ud65c\uc6a9 \ud65c\uc6a9 \ud65c\uc6a9 \ud65c\uc6a9 \ud65c\uc6a9 \ud65c\uc6a9 \ud65c\uc6a9 \ud65c\uc6a9 \ud65c\uc6a9 \ud65c\uc6a9 \ud65c\uc6a9 \ud65c\uc6a9 \ud65c\uc6a9 \ud65c\uc6a9 \ud65c\uc6a9 \ud65c\uc6a9 \ud65c\uc6a9 \ud65c\uc6a9 \ud65c\uc6a9 \ud65c\uc6a9 \ud65c\uc6a9 \ud65c\uc6a9 \ud65c\uc6a9 \ud65c\uc6a9 \ud65c\uc6a9 \ud65c\uc6a9 \ud65c\uc6a9 \ud65c\uc6a9 \ud65c\uc6a9 \ud65c\uc6a9 \ud65c\uc6a9 \ud65c\uc6a9 \ud65c\uc6a9"
    }
]